{
    "version": "6.0",
    "blockedNames": [
        {"name": "642654867", "note": "ប់ទោសឃើញក្នុង Website​"},
        {"name": "STAFF", "note": "Not Allow"},
        {"name": "SELF EMPLOYED", "note": "Not Allow"},
        {"name": "THAILAND", "note": "Not Allow"},
        {"name": "TRAVENOX GROUP CO., LTD.", "note": "200 ហើយ"},
        {"name": "VORAXIUM TRAVEL CO., LTD.", "note": "200 ហើយ"},
        {"name": "ZENQUARO TOURS CO., LTD.", "note": "200 ហើយ"},
        {"name": "KLYNTARA TECHNOLOGY CO., LTD.", "note": "200 ហើយ"},
        {"name": "QUENROLIC LOGISTICS CO., LTD.", "note": "200 ហើយ"},
        {"name": "DREZVORA CONSTRUCTION CO., LTD.", "note": "200 ហើយ"},
        {"name": "ZEPHLORIX TECHNOLOGY CO., LTD.", "note": "200 ហើយ"},
        {"name": "FAYLUNEX TRADING CO., LTD.", "note": "200 ហើយ"},
        {"name": "NEXZARIC CONSTRUCTION CO., LTD.", "note": "200 ហើយ"},
        {"name": "MIRVANTIX ENGINEERING CO., LTD.", "note": "200 ហើយ"},
        {"name": "SKYNOVIQ TRADING CO., LTD.", "note": "200 ហើយ"},
        {"name": "KORDANEX LOGISTICS CO., LTD.", "note": "200 ហើយ"},
        {"name": "========================", "SCAMMMMMMMM-PHEAROMLIST": "=========================="},
        {"name": "INDRI WIDIYANTI", "note": "(SCAM ONLINE)"},
        {"name": "SRIWAHYUNI MAKALALAG", "note": "(SCAM ONLINE)"},
        {"name": "ALFIANA ANASTHASIAD", "note": "(SCAM ONLINE)"},
        {"name": "MIACHO SIMANGUNSONG", "note": "(SCAM ONLINE)"},
        {"name": "DEWI IKA RIANA", "note": "(SCAM ONLINE)"},
        {"name": "LEVINA MARTHA", "note": "(SCAM ONLINE)"},
        {"name": "TRI ANGGITA", "note": "(SCAM ONLINE)"},
        {"name": "VILLEGAS JACKYLYN", "note": "(SCAM ONLINE)"},
        {"name": "IIS SUGANTI", "note": "(SCAM ONLINE)"},
        {"name": "INTAN NUR IANI DEAN", "note": "(SCAM ONLINE)"},
        {"name": "BAO RUNSONG", "note": "(SCAM ONLINE)"},
        {"name": "LI SONG", "note": "(SCAM ONLINE)"},
        {"name": "CAI CHENGJUNJIE", "note": "(SCAM ONLINE)"},
        {"name": "ZHONG BO", "note": "(SCAM ONLINE)"},
        {"name": "REN MINGXIN", "note": "(SCAM ONLINE)"},
        {"name": "ZHAO GANG", "note": "(SCAM ONLINE)"},
        {"name": "GOU GUOYI", "note": "(SCAM ONLINE)"},
        {"name": "WANG YUNFEI", "note": "(SCAM ONLINE)"},
        {"name": "LIU PINGJUN", "note": "(SCAM ONLINE)"},
        {"name": "TANG CAO", "note": "(SCAM ONLINE)"},
        {"name": "YANG XINYI", "note": "(SCAM ONLINE)"},
        {"name": "WANG JIE", "note": "(SCAM ONLINE)"},
        {"name": "HE ZHIPING", "note": "(SCAM ONLINE)"},
        {"name": "HUANG JIANBIAO", "note": "(SCAM ONLINE)"},
        {"name": "LIU LIANG", "note": "(SCAM ONLINE)"},
        {"name": "JIANG CHUNMING", "note": "(SCAM ONLINE)"},
        {"name": "QING MAIXIANG", "note": "(SCAM ONLINE)"},
        {"name": "ZHOU JIAXING", "note": "(SCAM ONLINE)"},
        {"name": "XIE BOYIN", "note": "(SCAM ONLINE)"},
        {"name": "RAO WEN", "note": "(SCAM ONLINE)"},
        {"name": "PAN CHAOYI", "note": "(SCAM ONLINE)"},
        {"name": "HUANG ZHIJIANG", "note": "(SCAM ONLINE)"},
        {"name": "LUO LI", "note": "(SCAM ONLINE)"},
        {"name": "CHEN MINGCAI", "note": "(SCAM ONLINE)"},
        {"name": "CHEN GUOLIN", "note": "(SCAM ONLINE)"},
        {"name": "WANG YAO", "note": "(SCAM ONLINE)"},
        {"name": "LI DONGYUN", "note": "(SCAM ONLINE)"},
        {"name": "MIN XIAOMUA", "note": "(SCAM ONLINE)"},
        {"name": "WANG SIDE", "note": "(SCAM ONLINE)"},
        {"name": "ZHANG RONGSHANG", "note": "(SCAM ONLINE)"},
        {"name": "CHENG YUHAO", "note": "(SCAM ONLINE)"},
        {"name": "HUANG JIAZING", "note": "(SCAM ONLINE)"},
        {"name": "ZHOU XIAOLONG", "note": "(SCAM ONLINE)"},
        {"name": "TANG QINGXIN", "note": "(SCAM ONLINE)"},
        {"name": "HUANG QIANJUN", "note": "(SCAM ONLINE)"},
        {"name": "LIU JUN", "note": "(SCAM ONLINE)"},
        {"name": "HE CONG", "note": "(SCAM ONLINE)"},
        {"name": "ZHOU XINJIAN", "note": "(SCAM ONLINE)"},
        {"name": "CAI QIMING", "note": "(SCAM ONLINE)"},
        {"name": "CHEN JUTENG", "note": "(SCAM ONLINE)"},
        {"name": "XIA BO", "note": "(SCAM ONLINE)"},
        {"name": "MA YULONG", "note": "(SCAM ONLINE)"},
        {"name": "YING ZIXIONG", "note": "(SCAM ONLINE)"},
        {"name": "PA SHENGBIN", "note": "(SCAM ONLINE)"},
        {"name": "TANG YUXIN", "note": "(SCAM ONLINE)"},
        {"name": "ZHANG ZEYUE", "note": "(SCAM ONLINE)"},
        {"name": "PAN JINYU", "note": "(SCAM ONLINE)"},
        {"name": "TAN SHULINK", "note": "(SCAM ONLINE)"},
        {"name": "MEI LIBAO", "note": "(SCAM ONLINE)"},
        {"name": "MA TAO", "note": "(SCAM ONLINE)"},
        {"name": "LANG XIAOHU", "note": "(SCAM ONLINE)"},
        {"name": "GAO JIANGHONG", "note": "(SCAM ONLINE)"},
        {"name": "WANG JUN", "note": "(SCAM ONLINE)"},
        {"name": "YANG KUNYAN", "note": "(SCAM ONLINE)"},
        {"name": "JIANG BIN", "note": "(SCAM ONLINE)"},
        {"name": "OU XIANFENG", "note": "(SCAM ONLINE)"},
        {"name": "GENG MAOMAO", "note": "(SCAM ONLINE)"},
        {"name": "BAI JUNXI", "note": "(SCAM ONLINE)"},
        {"name": "FANG FENG", "note": "(SCAM ONLINE)"},
        {"name": "LU SHANNAN", "note": "(SCAM ONLINE)"},
        {"name": "LUO PAN", "note": "(SCAM ONLINE)"},
        {"name": "ZHONG HUI", "note": "(SCAM ONLINE)"},
        {"name": "RAN SHIJIAN", "note": "(SCAM ONLINE)"},
        {"name": "LU XINJIAN", "note": "(SCAM ONLINE)"},
        {"name": "LI SHOUWU", "note": "(SCAM ONLINE)"},
        {"name": "CHEN HUA", "note": "(SCAM ONLINE)"},
        {"name": "MAO CHUANGUI", "note": "(SCAM ONLINE)"},
        {"name": "HUANG DIDU", "note": "(SCAM ONLINE)"},
        {"name": "CHEN YEA", "note": "(SCAM ONLINE)"},
        {"name": "XU YONGZHONG", "note": "(SCAM ONLINE)"},
        {"name": "ZHANG LEI", "note": "(SCAM ONLINE)"},
        {"name": "HE HUANG", "note": "(SCAM ONLINE)"},
        {"name": "ZHOU JIESEN", "note": "(SCAM ONLINE)"},
        {"name": "LUO YI", "note": "(SCAM ONLINE)"},
        {"name": "LONG ZHONGLIN", "note": "(SCAM ONLINE)"},
        {"name": "ZHANG CHENXUAN", "note": "(SCAM ONLINE)"},
        {"name": "YANG JINZHUO", "note": "(SCAM ONLINE)"},
        {"name": "LONG JIAWEI", "note": "(SCAM ONLINE)"},
        {"name": "LUO SHUAI", "note": "(SCAM ONLINE)"},
        {"name": "HU SHINJI", "note": "(SCAM ONLINE)"},
        {"name": "LUI HAIDONG", "note": "(SCAM ONLINE)"},
        {"name": "HOU DEZU", "note": "(SCAM ONLINE)"},
        {"name": "PENG JIAGEN", "note": "(SCAM ONLINE)"},
        {"name": "WU PEIYANG", "note": "(SCAM ONLINE)"},
        {"name": "LIANG GUOCHUN", "note": "(SCAM ONLINE)"},
        {"name": "ZHANG GUANFU", "note": "(SCAM ONLINE)"},
        {"name": "LI MINGYANG", "note": "(SCAM ONLINE)"},
        {"name": "WANG CHUNSHU", "note": "(SCAM ONLINE)"},
        {"name": "SU YINGHUAI", "note": "(SCAM ONLINE)"},
        {"name": "ZHAI MINJIE", "note": "(SCAM ONLINE)"},
        {"name": "QIN FUHAO", "note": "(SCAM ONLINE)"},
        {"name": "TAN 'ZHONGHAI", "note": "(SCAM ONLINE)"},
        {"name": "JIA SIAOBIN", "note": "(SCAM ONLINE)"},
        {"name": "TANG CHENG", "note": "(SCAM ONLINE)"},
        {"name": "LIU GUTING", "note": "(SCAM ONLINE)"},
        {"name": "LI JIECHEN", "note": "(SCAM ONLINE)"},
        {"name": "XU XINGRONG", "note": "(SCAM ONLINE)"},
        {"name": "XIE VENXIU", "note": "(SCAM ONLINE)"},
        {"name": "MENG FUGUI", "note": "(SCAM ONLINE)"},
        {"name": "YUAN CHAO", "note": "(SCAM ONLINE)"},
        {"name": "A WEI", "note": "(SCAM ONLINE)"},
        {"name": "WANG WEI", "note": "(SCAM ONLINE)"},
        {"name": "LIU KEXU", "note": "(SCAM ONLINE)"},
        {"name": "XU KE", "note": "(SCAM ONLINE)"},
        {"name": "RONG HAOYING", "note": "(SCAM ONLINE)"},
        {"name": "CHEN XIAOMING", "note": "(SCAM ONLINE)"},
        {"name": "WANG PEZXIN", "note": "(SCAM ONLINE)"},
        {"name": "WANG XIANGPENG", "note": "(SCAM ONLINE)"},
        {"name": "SUN MAOZHEN", "note": "(SCAM ONLINE)"},
        {"name": "LUO GUISHENG", "note": "(SCAM ONLINE)"},
        {"name": "JIANG YU", "note": "(SCAM ONLINE)"},
        {"name": "CHI SHAOQIANG", "note": "(SCAM ONLINE)"},
        {"name": "YANG SHIYANG", "note": "(SCAM ONLINE)"},
        {"name": "HUANG YONGSHENG", "note": "(SCAM ONLINE)"},
        {"name": "XIANG XANG", "note": "(SCAM ONLINE)"},
        {"name": "YANG ZHIYANG", "note": "(SCAM ONLINE)"},
        {"name": "XIE HUANGWEI", "note": "(SCAM ONLINE)"},
        {"name": "HE BINGYAO", "note": "(SCAM ONLINE)"},
        {"name": "PU HONGMING", "note": "(SCAM ONLINE)"},
        {"name": "CHEN PENG", "note": "(SCAM ONLINE)"},
        {"name": "LI CHUANLIANG", "note": "(SCAM ONLINE)"},
        {"name": "WANG SHIJI", "note": "(SCAM ONLINE)"},
        {"name": "SHUAI QI", "note": "(SCAM ONLINE)"},
        {"name": "LI GUANGZHAO", "note": "(SCAM ONLINE)"},
        {"name": "YANG ZHAIWEN", "note": "(SCAM ONLINE)"},
        {"name": "ZHOU ZHOU", "note": "(SCAM ONLINE)"},
        {"name": "YANG HAO", "note": "(SCAM ONLINE)"},
        {"name": "LI SUHAO", "note": "(SCAM ONLINE)"},
        {"name": "WU WENFU", "note": "(SCAM ONLINE)"},
        {"name": "BI TENGYUN", "note": "(SCAM ONLINE)"},
        {"name": "YA JUNGUO", "note": "(SCAM ONLINE)"},
        {"name": "LI LIANG", "note": "(SCAM ONLINE)"},
        {"name": "QIAN KUN", "note": "(SCAM ONLINE)"},
        {"name": "ZHONG ZHANGQUAN", "note": "(SCAM ONLINE)"},
        {"name": "ZHANG XINGYIN", "note": "(SCAM ONLINE)"},
        {"name": "JIA BAOLIN", "note": "(SCAM ONLINE)"},
        {"name": "JIA SHAOGUANG", "note": "(SCAM ONLINE)"},
        {"name": "YI YANGGANG", "note": "(SCAM ONLINE)"},
        {"name": "JIA JIACAI", "note": "(SCAM ONLINE)"},
        {"name": "XIANG JIE", "note": "(SCAM ONLINE)"},
        {"name": "YAN KANG", "note": "(SCAM ONLINE)"},
        {"name": "LUO YU", "note": "(SCAM ONLINE)"},
        {"name": "HUANG QIHUA", "note": "(SCAM ONLINE)"},
        {"name": "YANG SHEN", "note": "(SCAM ONLINE)"},
        {"name": "XIE JIAWEI", "note": "(SCAM ONLINE)"},
        {"name": "PENG XIAOZI", "note": "(SCAM ONLINE)"},
        {"name": "TANG XUELEI", "note": "(SCAM ONLINE)"},
        {"name": "CHEN YANG", "note": "(SCAM ONLINE)"},
        {"name": "CHEN ZHI", "note": "(SCAM ONLINE)"},
        {"name": "ZHOU MENGQI", "note": "(SCAM ONLINE)"},
        {"name": "DUAN XUEFEI", "note": "(SCAM ONLINE)"},
        {"name": "LI JIANGUO", "note": "(SCAM ONLINE)"},
        {"name": "LU JUNSHUAI", "note": "(SCAM ONLINE)"},
        {"name": "HUANG ZHENGQIAO", "note": "(SCAM ONLINE)"},
        {"name": "YU WEN", "note": "(SCAM ONLINE)"},
        {"name": "QIAN LONG", "note": "(SCAM ONLINE)"},
        {"name": "ZHANG HANCHENG", "note": "(SCAM ONLINE)"},
        {"name": "HUANG GUANGZHI", "note": "(SCAM ONLINE)"},
        {"name": "HE JIANSHENG", "note": "(SCAM ONLINE)"},
        {"name": "LUO QI", "note": "(SCAM ONLINE)"},
        {"name": "XUE YONGHENG", "note": "(SCAM ONLINE)"},
        {"name": "ZHANG HUAKOU", "note": "(SCAM ONLINE)"},
        {"name": "ZENG HONGYU", "note": "(SCAM ONLINE)"},
        {"name": "ZHOU CHICHONG", "note": "(SCAM ONLINE)"},
        {"name": "YI JIE", "note": "(SCAM ONLINE)"},
        {"name": "ZHAO MINHUA", "note": "(SCAM ONLINE)"},
        {"name": "LI YANG", "note": "(SCAM ONLINE)"},
        {"name": "JIANG GAOQING", "note": "(SCAM ONLINE)"},
        {"name": "LUO YIWAN", "note": "(SCAM ONLINE)"},
        {"name": "LIU TON", "note": "(SCAM ONLINE)"},
        {"name": "LIN SILONG", "note": "(SCAM ONLINE)"},
        {"name": "TIAN LIANG", "note": "(SCAM ONLINE)"},
        {"name": "ZENG WEI", "note": "(SCAM ONLINE)"},
        {"name": "GUO JIANGFEI", "note": "(SCAM ONLINE)"},
        {"name": "SHOU JIANQIANG", "note": "(SCAM ONLINE)"},
        {"name": "CHEN DAPENG", "note": "(SCAM ONLINE)"},
        {"name": "REN TUANPENG", "note": "(SCAM ONLINE)"},
        {"name": "ZHEN MIN", "note": "(SCAM ONLINE)"},
        {"name": "CHEN XIAODONG", "note": "(SCAM ONLINE)"},
        {"name": "HUANG JIANHAO", "note": "(SCAM ONLINE)"},
        {"name": "ZHANG TIAO", "note": "(SCAM ONLINE)"},
        {"name": "HU JIWEN", "note": "(SCAM ONLINE)"},
        {"name": "HU PENGFEI", "note": "(SCAM ONLINE)"},
        {"name": "TAO JISHUN", "note": "(SCAM ONLINE)"},
        {"name": "LU YANLI", "note": "(SCAM ONLINE)"},
        {"name": "LIN WEIHE", "note": "(SCAM ONLINE)"},
        {"name": "GUO MENGYANG", "note": "(SCAM ONLINE)"},
        {"name": "ZHOU LIJUN", "note": "(SCAM ONLINE)"},
        {"name": "XIAO TIAN", "note": "(SCAM ONLINE)"},
        {"name": "HE LI", "note": "(SCAM ONLINE)"},
        {"name": "ZHOU ZENGCHENG", "note": "(SCAM ONLINE)"},
        {"name": "WANG ZHICHAO", "note": "(SCAM ONLINE)"},
        {"name": "BAI XING", "note": "(SCAM ONLINE)"},
        {"name": "YE HAOJIE", "note": "(SCAM ONLINE)"},
        {"name": "PENG CANGHUA", "note": "(SCAM ONLINE)"},
        {"name": "PAN QIANZAN", "note": "(SCAM ONLINE)"},
        {"name": "SU WEIHUANG", "note": "(SCAM ONLINE)"},
        {"name": "CHEN SHIWEI", "note": "(SCAM ONLINE)"},
        {"name": "GUO WENJIE", "note": "(SCAM ONLINE)"},
        {"name": "WANG JUNJUN", "note": "(SCAM ONLINE)"},
        {"name": "HE JIANGMANG", "note": "(SCAM ONLINE)"},
        {"name": "PENG LEI", "note": "(SCAM ONLINE)"},
        {"name": "GUI JINYAO", "note": "(SCAM ONLINE)"},
        {"name": "LUI QIFEI", "note": "(SCAM ONLINE)"},
        {"name": "PHU HUI", "note": "(SCAM ONLINE)"},
        {"name": "LIU RENGUANG", "note": "(SCAM ONLINE)"},
        {"name": "YANG WENXIN", "note": "(SCAM ONLINE)"},
        {"name": "XU DUANSHEN", "note": "(SCAM ONLINE)"},
        {"name": "DING MINGYU", "note": "(SCAM ONLINE)"},
        {"name": "HE MANJUN", "note": "(SCAM ONLINE)"},
        {"name": "HE YUXIANG", "note": "(SCAM ONLINE)"},
        {"name": "XI ZHANGBING", "note": "(SCAM ONLINE)"},
        {"name": "TENG JUN", "note": "(SCAM ONLINE)"},
        {"name": "LIU JIAHAO", "note": "(SCAM ONLINE)"},
        {"name": "CHEN QIAZHI", "note": "(SCAM ONLINE)"},
        {"name": "HE ZHIXIN", "note": "(SCAM ONLINE)"},
        {"name": "LU MINJIE", "note": "(SCAM ONLINE)"},
        {"name": "WU YANG", "note": "(SCAM ONLINE)"},
        {"name": "GUO ZHANGYI", "note": "(SCAM ONLINE)"},
        {"name": "YUAN XIAOJIANG", "note": "(SCAM ONLINE)"},
        {"name": "LIU JIALIANG", "note": "(SCAM ONLINE)"},
        {"name": "MA YEABIN", "note": "(SCAM ONLINE)"},
        {"name": "FENG GANG", "note": "(SCAM ONLINE)"},
        {"name": "LUO QIANG", "note": "(SCAM ONLINE)"},
        {"name": "WANG PENGHUI", "note": "(SCAM ONLINE)"},
        {"name": "WANG SHUAITONG", "note": "(SCAM ONLINE)"},
        {"name": "WANG BIN", "note": "(SCAM ONLINE)"},
        {"name": "JING CHENWU", "note": "(SCAM ONLINE)"},
        {"name": "ZHAO TAI", "note": "(SCAM ONLINE)"},
        {"name": "ZHANG PENG", "note": "(SCAM ONLINE)"},
        {"name": "KANNEPOGU PRADEEPKUMAR", "note": "(SCAM ONLINE)"},
        {"name": "MANPREET SINGHHARBANSINGH", "note": "(SCAM ONLINE)"},
        {"name": "AJAY SINGH", "note": "(SCAM ONLINE)"},
        {"name": "YADAV BIKASH", "note": "(SCAM ONLINE)"},
        {"name": "SK HOSSAIHUR ZAMAN", "note": "(SCAM ONLINE)"},
        {"name": "MERUGU ROOPCHAND", "note": "(SCAM ONLINE)"},
        {"name": "AZEEMULLA SYEDAEJOZAMMED", "note": "(SCAM ONLINE)"},
        {"name": "KANNAPPAN NARAYANAN", "note": "(SCAM ONLINE)"},
        {"name": "MOHAMMED AZHARUDDIN", "note": "(SCAM ONLINE)"},
        {"name": "SHAIK MOHAMMADWAHID", "note": "(SCAM ONLINE)"},
        {"name": "AROUO A", "note": "(SCAM ONLINE)"},
        {"name": "ZULFE QUARHUSSANG", "note": "(SCAM ONLINE)"},
        {"name": "ELANGOVAN MATHIVANAN", "note": "(SCAM ONLINE)"},
        {"name": "HEMCING HRATHOJ", "note": "(SCAM ONLINE)"},
        {"name": "MOCHEN BER", "note": "(SCAM ONLINE)"},
        {"name": "SUPPIRAMANIAN GANESHPANDI", "note": "(SCAM ONLINE)"},
        {"name": "HAGENDRA SINGH", "note": "(SCAM ONLINE)"},
        {"name": "SUMIL KUMAR", "note": "(SCAM ONLINE)"},
        {"name": "DAREN DRASINGH", "note": "(SCAM ONLINE)"},
        {"name": "AM IT", "note": "(SCAM ONLINE)"},
        {"name": "LIU LISI", "note": "(SCAM ONLINE)"},
        {"name": "YUAN JEI", "note": "(SCAM ONLINE)"},
        {"name": "YAN JIANGWEI", "note": "(SCAM ONLINE)"},
        {"name": "WU FANGCHANG", "note": "(SCAM ONLINE)"},
        {"name": "CHEN SHIBIAO", "note": "(SCAM ONLINE)"},
        {"name": "GUO XIAOTONG", "note": "(SCAM ONLINE)"},
        {"name": "LUO JIANHOU", "note": "(SCAM ONLINE)"},
        {"name": "ZHANG BIN", "note": "(SCAM ONLINE)"},
        {"name": "XU KAIMI", "note": "(SCAM ONLINE)"},
        {"name": "KANNAN NARENDRA PANDIAN", "note": "(SCAM ONLINE)"},
        {"name": "CHINTA NAGESH", "note": "(SCAM ONLINE)"},
        {"name": "RAJANGAM NAGAPRAKASH", "note": "(SCAM ONLINE)"},
        {"name": "ANAN DAN HARI HARA SUDHAN", "note": "(SCAM ONLINE)"},
        {"name": "ALI JAVED", "note": "(SCAM ONLINE)"},
        {"name": "MOHAMMAD IRSHAD SHYARA BEGAM", "note": "(SCAM ONLINE)"},
        {"name": "SUNNY", "note": "(SCAM ONLINE)"},
        {"name": "PRASAD VISHNU", "note": "(SCAM ONLINE)"},
        {"name": "DILEEPKUMAR DEEPAK", "note": "(SCAM ONLINE)"},
        {"name": "MYFOOZ ASIF SHAIKH", "note": "(SCAM ONLINE)"},
        {"name": "SAHANI SANTOSH", "note": "(SCAM ONLINE)"},
        {"name": "CHAN DAN KUMAR", "note": "(SCAM ONLINE)"},
        {"name": "ANIL KUMAR", "note": "(SCAM ONLINE)"},
        {"name": "ALEXANDER ANISH JOSE RAJ", "note": "(SCAM ONLINE)"},
        {"name": "VELU VELANDI MAHESH", "note": "(SCAM ONLINE)"},
        {"name": "GOTAMLAL POTIDAN", "note": "(SCAM ONLINE)"},
        {"name": "ASWAL AKSHAT", "note": "(SCAM ONLINE)"},
        {"name": "JAYAPRAKASH SHARAN DAVID", "note": "(SCAM ONLINE)"},
        {"name": "JANGAMKAR MOHIT", "note": "(SCAM ONLINE)"},
        {"name": "SNA VEEN", "note": "(SCAM ONLINE)"},
        {"name": "KURAKALA SUDHAKAR", "note": "(SCAM ONLINE)"},
        {"name": "KMNB CHANDXASEKMAR", "note": "(SCAM ONLINE)"},
        {"name": "ANTONYVIJAY JOMNBOSCO", "note": "(SCAM ONLINE)"},
        {"name": "NEELAKANDAN JAGAN", "note": "(SCAM ONLINE)"},
        {"name": "EHASAN MIYAN", "note": "(SCAM ONLINE)"},
        {"name": "GO LU", "note": "(SCAM ONLINE)"},
        {"name": "RAMAVATH SIVAKUMAR", "note": "(SCAM ONLINE)"},
        {"name": "ADARIJA GAN", "note": "(SCAM ONLINE)"},
        {"name": "RAJUKU MAR", "note": "(SCAM ONLINE)"},
        {"name": "GUFRAN KHAN", "note": "(SCAM ONLINE)"},
        {"name": "DODDAMOLATHE DORESWAMYNAGESHA", "note": "(SCAM ONLINE)"},
        {"name": "PATEL SINGH", "note": "(SCAM ONLINE)"},
        {"name": "MADUHUNN IHALIHAL", "note": "(SCAM ONLINE)"},
        {"name": "GURBALASUPP IRAMAHI", "note": "(SCAM ONLINE)"},
        {"name": "LIMARAVIN SON", "note": "(SCAM ONLINE)"},
        {"name": "NEMALA JAMES", "note": "(SCAM ONLINE)"},
        {"name": "MALLAPU DHARMARAJU", "note": "(SCAM ONLINE)"},
        {"name": "LATHEEF ASHIK", "note": "(SCAM ONLINE)"},
        {"name": "DINOOP ACHARYPD", "note": "(SCAM ONLINE)"},
        {"name": "ANANDAN NITHISHRAJ", "note": "(SCAM ONLINE)"},
        {"name": "PRE ME", "note": "(SCAM ONLINE)"},
        {"name": "RAJAT PUNDIR", "note": "(SCAM ONLINE)"},
        {"name": "KRISHAN CHAND", "note": "(SCAM ONLINE)"},
        {"name": "BSAIVAMSI KRISHNA", "note": "(SCAM ONLINE)"},
        {"name": "ARJUN PRABHAK", "note": "(SCAM ONLINE)"},
        {"name": "SELVAI NODH", "note": "(SCAM ONLINE)"},
        {"name": "AHTISHAM ASLAM", "note": "(SCAM ONLINE)"},
        {"name": "JEILEO ROBISON", "note": "(SCAM ONLINE)"},
        {"name": "MODASSI RNAZAR", "note": "(SCAM ONLINE)"},
        {"name": "RAJENDRAN DHARMARAJ", "note": "(SCAM ONLINE)"},
        {"name": "SELVARASU VERAPPAN", "note": "(SCAM ONLINE)"},
        {"name": "ARICHANDIRAN LOGAMOORTHY", "note": "(SCAM ONLINE)"},
        {"name": "RADHA KRISHNAN SURYA", "note": "(SCAM ONLINE)"},
        {"name": "A AJAY KUMAR", "note": "(SCAM ONLINE)"},
        {"name": "RANGADURAI PARTHIBAN", "note": "(SCAM ONLINE)"},
        {"name": "SHAIKH DANIYAL MOHAMMED SALIM", "note": "(SCAM ONLINE)"},
        {"name": "M SRI KARTHIK", "note": "(SCAM ONLINE)"},
        {"name": "AB HISHEK YADAV", "note": "(SCAM ONLINE)"},
        {"name": "RAJ MANU", "note": "(SCAM ONLINE)"},
        {"name": "MOHD ANZAR KHAN", "note": "(SCAM ONLINE)"},
        {"name": "ATIQURR HMAM", "note": "(SCAM ONLINE)"},
        {"name": "MD JAMSHED KHAN", "note": "(SCAM ONLINE)"},
        {"name": "MONISH A", "note": "(SCAM ONLINE)"},
        {"name": "RAMAKRISHNAN SABARIGOWSHIKAN", "note": "(SCAM ONLINE)"},
        {"name": "MOHAMMED JABEER", "note": "(SCAM ONLINE)"},
        {"name": "KOPPATIIL BHASKARAN SUJEESH", "note": "(SCAM ONLINE)"},
        {"name": "RAILAVATH SANTOSH NAYAK", "note": "(SCAM ONLINE)"},
        {"name": "MOHAMMAD FAYAZ", "note": "(SCAM ONLINE)"},
        {"name": "POLASA SHYMU", "note": "(SCAM ONLINE)"},
        {"name": "JITHIN JOHNSON", "note": "(SCAM ONLINE)"},
        {"name": "SREE KUMARAN ADITHYAN", "note": "(SCAM ONLINE)"},
        {"name": "THADATHIL LEKSHMANAN", "note": "(SCAM ONLINE)"},
        {"name": "SANKAR GOURY", "note": "(SCAM ONLINE)"},
        {"name": "ANIL KUMARASHAK", "note": "(SCAM ONLINE)"},
        {"name": "ALAN SAMUEL", "note": "(SCAM ONLINE)"},
        {"name": "MALIKMOHAMMED ALIFHUSSAIN", "note": "(SCAM ONLINE)"},
        {"name": "HAFIZMUHAMMAD UMERSHAFIQ", "note": "(SCAM ONLINE)"},
        {"name": "HAMZA ALI", "note": "(SCAM ONLINE)"},
        {"name": "FEFF JAMIL", "note": "(SCAM ONLINE)"},
        {"name": "SA IM", "note": "(SCAM ONLINE)"},
        {"name": "YAQOOB ROBINSON", "note": "(SCAM ONLINE)"},
        {"name": "WASEFM RAJAMUAMMAD", "note": "(SCAM ONLINE)"},
        {"name": "JUNAID ASGHAR", "note": "(SCAM ONLINE)"},
        {"name": "ASHRAF HUMAYOON", "note": "(SCAM ONLINE)"},
        {"name": "ZIAMUHAMMAD AHSAN", "note": "(SCAM ONLINE)"},
        {"name": "MUHAMMAD SHABBEIR", "note": "(SCAM ONLINE)"},
        {"name": "WALEED ALI", "note": "(SCAM ONLINE)"},
        {"name": "MUHAMMAD SADDAM", "note": "(SCAM ONLINE)"},
        {"name": "ASAD KHAN", "note": "(SCAM ONLINE)"},
        {"name": "SHAROZE KHAN", "note": "(SCAM ONLINE)"},
        {"name": "KAPIL JOSHI", "note": "(SCAM ONLINE)"},
        {"name": "SULOK RATOSTOGI", "note": "(SCAM ONLINE)"},
        {"name": "AJAYA SARKI", "note": "(SCAM ONLINE)"},
        {"name": "KAMALROIB AJAGAIN", "note": "(SCAM ONLINE)"},
        {"name": "PUKARTIIU NGLAMO", "note": "(SCAM ONLINE)"},
        {"name": "ANJAL GIRI", "note": "(SCAM ONLINE)"},
        {"name": "VTTAM GHISING", "note": "(SCAM ONLINE)"},
        {"name": "DIPESH SHAHI", "note": "(SCAM ONLINE)"},
        {"name": "SAMMAN ADHIKARI", "note": "(SCAM ONLINE)"},
        {"name": "RONEY GURUNG", "note": "(SCAM ONLINE)"},
        {"name": "MASUD RANA", "note": "(SCAM ONLINE)"},
        {"name": "JA SIM", "note": "(SCAM ONLINE)"},
        {"name": "MDTAREQ HOSSAIN", "note": "(SCAM ONLINE)"},
        {"name": "ABDUL RAKIB", "note": "(SCAM ONLINE)"},
        {"name": "MDSHUMON HOSSAIN", "note": "(SCAM ONLINE)"},
        {"name": "MDSAIFUL ISLAM", "note": "(SCAM ONLINE)"},
        {"name": "MDABDULLAH ALJABER", "note": "(SCAM ONLINE)"},
        {"name": "MD SIAM", "note": "(SCAM ONLINE)"},
        {"name": "ANTHONY GOMES", "note": "(SCAM ONLINE)"},
        {"name": "ALIF MAHMUD", "note": "(SCAM ONLINE)"},
        {"name": "MDFOYSAL KABIR", "note": "(SCAM ONLINE)"},
        {"name": "HASAN MAHAMUD", "note": "(SCAM ONLINE)"},
        {"name": "MUHAMMADHASAN UZZAMANHASAN", "note": "(SCAM ONLINE)"},
        {"name": "MDRIHAN SHARIF", "note": "(SCAM ONLINE)"},
        {"name": "LAHTAW SENG PAN", "note": "(SCAM ONLINE)"},
        {"name": "FERDIAN SYAH", "note": "(SCAM ONLINE)"},
        {"name": "EDWAN NABI", "note": "(SCAM ONLINE)"},
        {"name": "ALDIPRAT AMA", "note": "(SCAM ONLINE)"},
        {"name": "MIQBALARI FIN", "note": "(SCAM ONLINE)"},
        {"name": "MAL FARIZI", "note": "(SCAM ONLINE)"},
        {"name": "ANDRE SEGHPUIQR", "note": "(SCAM ONLINE)"},
        {"name": "DWISAPUTRO ROMANDONI", "note": "(SCAM ONLINE)"},
        {"name": "MYUSAI FARID", "note": "(SCAM ONLINE)"},
        {"name": "GEDERIKA YASA", "note": "(SCAM ONLINE)"},
        {"name": "FIRZATULLAH RAMAO", "note": "(SCAM ONLINE)"},
        {"name": "GANDY IRAWAN", "note": "(SCAM ONLINE)"},
        {"name": "WIKOYOLAN DA", "note": "(SCAM ONLINE)"},
        {"name": "AGUNG FAHRIZAN", "note": "(SCAM ONLINE)"},
        {"name": "SYAHFURA HELDI", "note": "(SCAM ONLINE)"},
        {"name": "ANDRI PUTRA", "note": "(SCAM ONLINE)"},
        {"name": "ALFREDO CHRISTIANSUMURA", "note": "(SCAM ONLINE)"},
        {"name": "SIM ON", "note": "(SCAM ONLINE)"},
        {"name": "GILANG PRATAMA", "note": "(SCAM ONLINE)"},
        {"name": "MUHAMMAD FAISAL", "note": "(SCAM ONLINE)"},
        {"name": "STEVANUSROD RIGOPUSUNG", "note": "(SCAM ONLINE)"},
        {"name": "RESA HARUN", "note": "(SCAM ONLINE)"},
        {"name": "RAMSESPALEN TINOKAPARANG", "note": "(SCAM ONLINE)"},
        {"name": "WILIARDIAN SYAH", "note": "(SCAM ONLINE)"},
        {"name": "FAUZAN ANSHARY", "note": "(SCAM ONLINE)"},
        {"name": "DANG VAN LAP", "note": "(SCAM ONLINE)"},
        {"name": "PHAMMANH DUNG", "note": "(SCAM ONLINE)"},
        {"name": "LEANH DUC", "note": "(SCAM ONLINE)"},
        {"name": "NGUYEN NGOCLONG", "note": "(SCAM ONLINE)"},
        {"name": "LEHOANG THANH", "note": "(SCAM ONLINE)"},
        {"name": "LEVAN PHU", "note": "(SCAM ONLINE)"},
        {"name": "TRANTUAN ANH", "note": "(SCAM ONLINE)"},
        {"name": "NGUYEN SINGOCPHUC", "note": "(SCAM ONLINE)"},
        {"name": "NGUYEN THAIHA", "note": "(SCAM ONLINE)"},
        {"name": "TRAN IETHOANG", "note": "(SCAM ONLINE)"},
        {"name": "LUAN VANPHONG", "note": "(SCAM ONLINE)"},
        {"name": "HOANG VAN THIEM", "note": "(SCAM ONLINE)"},
        {"name": "VUVIET ANH", "note": "(SCAM ONLINE)"},
        {"name": "NGUYEN HUNGTHINH", "note": "(SCAM ONLINE)"},
        {"name": "PHAM TUANLOC", "note": "(SCAM ONLINE)"},
        {"name": "NGUYEN THANH DAT", "note": "(SCAM ONLINE)"},
        {"name": "NGUYEN THANHHUNG", "note": "(SCAM ONLINE)"},
        {"name": "NGUYEN THANHTU", "note": "(SCAM ONLINE)"},
        {"name": "BECKLEY VICTOR", "note": "(SCAM ONLINE)"},
        {"name": "GOLOKEH LEVI BASS", "note": "(SCAM ONLINE)"},
        {"name": "DARIUSA SACKE", "note": "(SCAM ONLINE)"},
        {"name": "GIDI AUGUSTUS BLAISE FIAGBOR", "note": "(SCAM ONLINE)"},
        {"name": "KIMOTHO JUSPER WAHOME", "note": "(SCAM ONLINE)"},
        {"name": "KAMANDE JOHN MATINDI", "note": "(SCAM ONLINE)"},
        {"name": "HA THI NGOC", "note": "(SCAM ONLINE)"},
        {"name": "NGUYENTHANH CHAM", "note": "(SCAM ONLINE)"},
        {"name": "VOTRANHANH NHAN", "note": "(SCAM ONLINE)"},
        {"name": "PHAMTHI QUYNHANH", "note": "(SCAM ONLINE)"},
        {"name": "VI THI HY", "note": "(SCAM ONLINE)"},
        {"name": "LEHOANG GIAHAN", "note": "(SCAM ONLINE)"},
        {"name": "LUCTHI HUONG", "note": "(SCAM ONLINE)"},
        {"name": "LOC THANH THUY", "note": "(SCAM ONLINE)"},
        {"name": "NGUYEN THI MY HUYENK", "note": "(SCAM ONLINE)"},
        {"name": "TRAN THI THU HUONG", "note": "(SCAM ONLINE)"},
        {"name": "NGUYENTHI TUYETMAI", "note": "(SCAM ONLINE)"},
        {"name": "HUYNH HONGTHU", "note": "(SCAM ONLINE)"},
        {"name": "HUANG LINA", "note": "(SCAM ONLINE)"},
        {"name": "HUAGYOU JOE", "note": "(SCAM ONLINE)"},
        {"name": "LIMAN NI", "note": "(SCAM ONLINE)"},
        {"name": "LIYAN MING", "note": "(SCAM ONLINE)"},
        {"name": "LIFU YANG", "note": "(SCAM ONLINE)"},
        {"name": "PENG FANG", "note": "(SCAM ONLINE)"},
        {"name": "YANG TIANYU", "note": "(SCAM ONLINE)"},
        {"name": "CENG LU", "note": "(SCAM ONLINE)"},
        {"name": "ZHU VEIYAN", "note": "(SCAM ONLINE)"},
        {"name": "TONGYN HAN", "note": "(SCAM ONLINE)"},
        {"name": "LMELDA AGUSTINA SIHOMBING", "note": "(SCAM ONLINE)"},
        {"name": "INDAHAPRILE ANTI", "note": "(SCAM ONLINE)"},
        {"name": "PUTRI ANDINI", "note": "(SCAM ONLINE)"},
        {"name": "WAHYUN INGSIH", "note": "(SCAM ONLINE)"},
        {"name": "NENENG DEWI HARTATI", "note": "(SCAM ONLINE)"},
        {"name": "DINDI KHOLISA PUTRI", "note": "(SCAM ONLINE)"},
        {"name": "YUNITA POLI", "note": "(SCAM ONLINE)"},
        {"name": "JENIFERWANGEN GETAN", "note": "(SCAM ONLINE)"},
        {"name": "PRISCILIA JINIFER BANSALENG", "note": "(SCAM ONLINE)"},
        {"name": "MARCELA ANGELINA", "note": "(SCAM ONLINE)"},
        {"name": "YUNIFEBRIANTI BONE", "note": "(SCAM ONLINE)"},
        {"name": "LAVEGA LOMBOAN", "note": "(SCAM ONLINE)"},
        {"name": "WUTT HMONOO", "note": "(SCAM ONLINE)"},
        {"name": "CHERRY FISH", "note": "(SCAM ONLINE)"},
        {"name": "NANGKHM MAI", "note": "(SCAM ONLINE)"},
        {"name": "PERVAIZ SAIQA", "note": "(SCAM ONLINE)"},
        {"name": "TSHA LAMA", "note": "(SCAM ONLINE)"},
        {"name": "MUSILA MERCY MWENDE", "note": "(SCAM ONLINE)"},
        {"name": "PENAMARANA THAFHARIDA", "note": "(SCAM ONLINE)"},
        {"name": "KA SHISH", "note": "(SCAM ONLINE)"},
        {"name": "KUNI KA", "note": "(SCAM ONLINE)"},
        {"name": "SARANYA JEEVA", "note": "(SCAM ONLINE)"},
        {"name": "PAVI THRA", "note": "(SCAM ONLINE)"},
        {"name": "ASNA SALEEM", "note": "(SCAM ONLINE)"},
        {"name": "VISMAYA SANYAY", "note": "(SCAM ONLINE)"},
        {"name": "ARCHANA KRISHNAN", "note": "(SCAM ONLINE)"},
        {"name": "NAGMA FIRDAUS", "note": "(SCAM ONLINE)"},
        {"name": "MAN SI", "note": "(SCAM ONLINE)"},
        {"name": "CHITRA DEVI", "note": "(SCAM ONLINE)"},
        {"name": "KAV YA", "note": "(SCAM ONLINE)"},
        {"name": "NAMRI THA", "note": "(SCAM ONLINE)"},
        {"name": "KALYANI NEBARTHI", "note": "(SCAM ONLINE)"},
        {"name": "SHAIKH AAMINA", "note": "(SCAM ONLINE)"},
        {"name": "LI XINGYIN", "note": "(SCAM ONLINE)"},
        {"name": "YI ANDONG", "note": "(SCAM ONLINE)"},
        {"name": "XUE KUAN", "note": "(SCAM ONLINE)"},
        {"name": "SHENG HONGLIANG", "note": "(SCAM ONLINE)"},
        {"name": "DU KE", "note": "(SCAM ONLINE)"},
        {"name": "HUANG QUE", "note": "(SCAM ONLINE)"},
        {"name": "HE QI FA", "note": "(SCAM ONLINE)"},
        {"name": "QIU CHENG", "note": "(SCAM ONLINE)"},
        {"name": "WANG ZIYU", "note": "(SCAM ONLINE)"},
        {"name": "CEN GUO JUN", "note": "(SCAM ONLINE)"},
        {"name": "WANG DING YUAN", "note": "(SCAM ONLINE)"},
        {"name": "WANG WU BING", "note": "(SCAM ONLINE)"},
        {"name": "LI HAO LI", "note": "(SCAM ONLINE)"},
        {"name": "WU QI FAN", "note": "(SCAM ONLINE)"},
        {"name": "CHEN YUSHE", "note": "(SCAM ONLINE)"},
        {"name": "CHEN HAISEN", "note": "(SCAM ONLINE)"},
        {"name": "GAN ZHIWEI", "note": "(SCAM ONLINE)"},
        {"name": "FANG FAN", "note": "(SCAM ONLINE)"},
        {"name": "TANG ZHENGGUO", "note": "(SCAM ONLINE)"},
        {"name": "HUANG TIANXIN", "note": "(SCAM ONLINE)"},
        {"name": "MENG LONGFENG", "note": "(SCAM ONLINE)"},
        {"name": "YUAN LICHANG", "note": "(SCAM ONLINE)"},
        {"name": "JIANG BINGQIAO", "note": "(SCAM ONLINE)"},
        {"name": "QIAN ZHONG", "note": "(SCAM ONLINE)"},
        {"name": "LIANG ZHEZHAO", "note": "(SCAM ONLINE)"},
        {"name": "ZHU YONGQIANG", "note": "(SCAM ONLINE)"},
        {"name": "WU JIE", "note": "(SCAM ONLINE)"},
        {"name": "LAI PO YEN", "note": "(SCAM ONLINE)"},
        {"name": "CUI TENG SENG", "note": "(SCAM ONLINE)"},
        {"name": "MO JIANHAO", "note": "(SCAM ONLINE)"},
        {"name": "TANG CHAO", "note": "(SCAM ONLINE)"},
        {"name": "YUAN TAO", "note": "(SCAM ONLINE)"},
        {"name": "GE YIYUAN", "note": "(SCAM ONLINE)"},
        {"name": "LEI CHOG", "note": "(SCAM ONLINE)"},
        {"name": "WANG SINMING", "note": "(SCAM ONLINE)"},
        {"name": "LIU JING YI", "note": "(SCAM ONLINE)"},
        {"name": "LIU KAI", "note": "(SCAM ONLINE)"},
        {"name": "YANG LONG GAING", "note": "(SCAM ONLINE)"},
        {"name": "LI HUI", "note": "(SCAM ONLINE)"},
        {"name": "PENG YANG", "note": "(SCAM ONLINE)"},
        {"name": "FU BO", "note": "(SCAM ONLINE)"},
        {"name": "ZOU DEZHENG", "note": "(SCAM ONLINE)"},
        {"name": "JIANG TINGUI", "note": "(SCAM ONLINE)"},
        {"name": "HE XIAO AN", "note": "(SCAM ONLINE)"},
        {"name": "YIN JUN", "note": "(SCAM ONLINE)"},
        {"name": "LIU HUAIQI", "note": "(SCAM ONLINE)"},
        {"name": "LUO XIAODONG", "note": "(SCAM ONLINE)"},
        {"name": "WANG CHENGLONG", "note": "(SCAM ONLINE)"},
        {"name": "ZHOU HENG", "note": "(SCAM ONLINE)"},
        {"name": "JIANG BANGCHAO", "note": "(SCAM ONLINE)"},
        {"name": "TONG GANG", "note": "(SCAM ONLINE)"},
        {"name": "MA AN BO", "note": "(SCAM ONLINE)"},
        {"name": "YUAN SHENG BAO", "note": "(SCAM ONLINE)"},
        {"name": "WANG SHENG YU", "note": "(SCAM ONLINE)"},
        {"name": "WANG DE QIANG", "note": "(SCAM ONLINE)"},
        {"name": "SHEN ZHOU", "note": "(SCAM ONLINE)"},
        {"name": "HU LIANG", "note": "(SCAM ONLINE)"},
        {"name": "KUANG HANG AN", "note": "(SCAM ONLINE)"},
        {"name": "ZHANG JIAN", "note": "(SCAM ONLINE)"},
        {"name": "ALDI PRATAMA", "note": "(SCAM ONLINE)"},
        {"name": "NOPRI WANDI LUBIS", "note": "(SCAM ONLINE)"},
        {"name": "IMANUEL CHRISYE KATUUK", "note": "(SCAM ONLINE)"},
        {"name": "MOH RIZRY A HARUM", "note": "(SCAM ONLINE)"},
        {"name": "DIMAS ARIEF PRASAYTA", "note": "(SCAM ONLINE)"},
        {"name": "NOVAL MULIANSYAH", "note": "(SCAM ONLINE)"},
        {"name": "GLEMDIMO PITER", "note": "(SCAM ONLINE)"},
        {"name": "EINSEN RUSTIN LAZARUS", "note": "(SCAM ONLINE)"},
        {"name": "BOBY HERMANTO", "note": "(SCAM ONLINE)"},
        {"name": "FERRIAN SETIAWAN", "note": "(SCAM ONLINE)"},
        {"name": "FAHRI DWL SAPUTRA", "note": "(SCAM ONLINE)"},
        {"name": "GLEND DARENO", "note": "(SCAM ONLINE)"},
        {"name": "ROHID AKBAR", "note": "(SCAM ONLINE)"},
        {"name": "ROBIN FERNANDO", "note": "(SCAM ONLINE)"},
        {"name": "SELWA RAJ", "note": "(SCAM ONLINE)"},
        {"name": "NOOR UL ISLAM", "note": "(SCAM ONLINE)"},
        {"name": "AKSEER USAMA", "note": "(SCAM ONLINE)"},
        {"name": "ABBAS MUNAZAR", "note": "(SCAM ONLINE)"},
        {"name": "RIAZ MIAN ABDUL", "note": "(SCAM ONLINE)"},
        {"name": "ALI BABAR", "note": "(SCAM ONLINE)"},
        {"name": "SHAHBBIR MUHAMMAD GHULAM", "note": "(SCAM ONLINE)"},
        {"name": "NASIR MUHAMMAD HASEEB", "note": "(SCAM ONLINE)"},
        {"name": "THREEMANNA DILAN CHATHURAN", "note": "(SCAM ONLINE)"},
        {"name": "SAPUTRA", "note": "(SCAM ONLINE)"},
        {"name": "FAZAR RAMDHANI YUSUP", "note": "(SCAM ONLINE)"},
        {"name": "M AKBAR RIADI", "note": "(SCAM ONLINE)"},
        {"name": "ZHU MAO HUA", "note": "(SCAM ONLINE)"},
        {"name": "SARAH NURALIZAH", "note": "(SCAM ONLINE)"},
        {"name": "WANG LI", "note": "(SCAM ONLINE)"},
        {"name": "ROSELINDA MARGAREFHA", "note": "(SCAM ONLINE)"},
        {"name": "NAZWA SALWANISA", "note": "(SCAM ONLINE)"},
        {"name": "RACHEL MONICALEMBONG", "note": "(SCAM ONLINE)"},
        {"name": "ZAINAH BALQIS", "note": "(SCAM ONLINE)"},
        {"name": "DESTIYANI PUSPHWINDH", "note": "(SCAM ONLINE)"},
        {"name": "GRACIELA MIR ANDATOMUKA", "note": "(SCAM ONLINE)"},
        {"name": "CANNY FLUENCY", "note": "(SCAM ONLINE)"},
        {"name": "NGUYEN THI HANG", "note": "(SCAM ONLINE)"},
        {"name": "GAO WEIFENG", "note": "(SCAM ONLINE)"},
        {"name": "ZHAO XIAOLI", "note": "(SCAM ONLINE)"},
        {"name": "WANG YI", "note": "(SCAM ONLINE)"},
        {"name": "WEI ZHENPENG", "note": "(SCAM ONLINE)"},
        {"name": "CHEN FEIYU", "note": "(SCAM ONLINE)"},
        {"name": "LIU XIAOLONG", "note": "(SCAM ONLINE)"},
        {"name": "LIU YIFAN", "note": "(SCAM ONLINE)"},
        {"name": "YANG DEQIANG", "note": "(SCAM ONLINE)"},
        {"name": "LI KE", "note": "(SCAM ONLINE)"},
        {"name": "GAO CHENG", "note": "(SCAM ONLINE)"},
        {"name": "WANG XIN", "note": "(SCAM ONLINE)"},
        {"name": "WEI ZHICAI", "note": "(SCAM ONLINE)"},
        {"name": "LIN ZHIMINH", "note": "(SCAM ONLINE)"},
        {"name": "LUO ZHENTENG", "note": "(SCAM ONLINE)"},
        {"name": "CHEN RONGXUAN", "note": "(SCAM ONLINE)"},
        {"name": "ZHONG HONGJIN", "note": "(SCAM ONLINE)"},
        {"name": "PENG BO", "note": "(SCAM ONLINE)"},
        {"name": "ZHANG KEWEI", "note": "(SCAM ONLINE)"},
        {"name": "LONG CHUNHONG", "note": "(SCAM ONLINE)"},
        {"name": "MIAO XIAOQIANG", "note": "(SCAM ONLINE)"},
        {"name": "MIA MD PARVEJ", "note": "(SCAM ONLINE)"},
        {"name": "HOSSAIN NOMAN", "note": "(SCAM ONLINE)"},
        {"name": "ALAM MD MARUF SHAHRIAR", "note": "(SCAM ONLINE)"},
        {"name": "HOSEN MD AJIM", "note": "(SCAM ONLINE)"},
        {"name": "SHIKDER MD SHIPON", "note": "(SCAM ONLINE)"},
        {"name": "HOSSAIN MD TANIM", "note": "(SCAM ONLINE)"},
        {"name": "HASAN NAZMUL", "note": "(SCAM ONLINE)"},
        {"name": "HOSSAIN MD TAKBIR", "note": "(SCAM ONLINE)"},
        {"name": "MOLLAH MD FOYSAL", "note": "(SCAM ONLINE)"},
        {"name": "HOSSEN MD RAKIB", "note": "(SCAM ONLINE)"},
        {"name": "XU CHONGNAN", "note": "(SCAM ONLINE)"},
        {"name": "WANG XULONG", "note": "(SCAM ONLINE)"},
        {"name": "MA YALU", "note": "(SCAM ONLINE)"},
        {"name": "SU HONGBIN", "note": "(SCAM ONLINE)"},
        {"name": "XING DI", "note": "(SCAM ONLINE)"},
        {"name": "TAN YUANYUAN", "note": "(SCAM ONLINE)"},
        {"name": "SU YUPEI", "note": "(SCAM ONLINE)"},
        {"name": "LIU SIXIAN", "note": "(SCAM ONLINE)"},
        {"name": "LI GOUBO", "note": "(SCAM ONLINE)"},
        {"name": "LIU TIANQI", "note": "(SCAM ONLINE)"},
        {"name": "HUANG PENGCHENG", "note": "(SCAM ONLINE)"},
        {"name": "XONG QIANG", "note": "(SCAM ONLINE)"},
        {"name": "CHANG ENQI", "note": "(SCAM ONLINE)"},
        {"name": "HE KANG", "note": "(SCAM ONLINE)"},
        {"name": "HOSSAIN MD AFNAN", "note": "(SCAM ONLINE)"},
        {"name": "MILU KHALID HASAN", "note": "(SCAM ONLINE)"},
        {"name": "ASIF MD ABUL BASHAR", "note": "(SCAM ONLINE)"},
        {"name": "SHOWROV MIZANUR RAHMAN", "note": "(SCAM ONLINE)"},
        {"name": "RAHMAN SK MAHAFUJUR", "note": "(SCAM ONLINE)"},
        {"name": "HASIB ABDULLAH AL", "note": "(SCAM ONLINE)"},
        {"name": "ISLAM ZAHIRUL", "note": "(SCAM ONLINE)"},
        {"name": "ISLAM MD EMDADUL", "note": "(SCAM ONLINE)"},
        {"name": "HOSSAIN SAMIR", "note": "(SCAM ONLINE)"},
        {"name": "BHOWMIK PROTAB", "note": "(SCAM ONLINE)"},
        {"name": "ROSHID MD MAMUN", "note": "(SCAM ONLINE)"},
        {"name": "OVI MD AMIR HAMZA", "note": "(SCAM ONLINE)"},
        {"name": "UDEH PROMISE KELECHI", "note": "(SCAM ONLINE)"},
        {"name": "KIM THAT LOC", "note": "(SCAM ONLINE)"},
        {"name": "LI CHANGDA", "note": "(SCAM ONLINE)"},
        {"name": "RONEY NAZMUL KABIR", "note": "(SCAM ONLINE)"},
        {"name": "HAN SOE THU", "note": "(SCAM ONLINE)"},
        {"name": "THET AUNG", "note": "(SCAM ONLINE)"},
        {"name": "THET PAING SOE", "note": "(SCAM ONLINE)"},
        {"name": "MIN THET PAING SOE", "note": "(SCAM ONLINE)"},
        {"name": "SAW HTOO WAH", "note": "(SCAM ONLINE)"},
        {"name": "THET OO MAUNG", "note": "(SCAM ONLINE)"},
        {"name": "HLA MIN THU", "note": "(SCAM ONLINE)"},
        {"name": "ABDELWAHAB MAGED HAITHAM MAGED", "note": "(SCAM ONLINE)"},
        {"name": "THACH THONA", "note": "(SCAM ONLINE)"},
        {"name": "WANG XUN", "note": "(SCAM ONLINE)"},
        {"name": "CHERRY", "note": "(SCAM ONLINE)"},
        {"name": "AYE WINE SOE", "note": "(SCAM ONLINE)"},
        {"name": "LAI XIAOLIN", "note": "(SCAM ONLINE)"},
        {"name": "GAZA RODALYN", "note": "(SCAM ONLINE)"},
        {"name": "LI TAO", "note": "(SCAM ONLINE)"},
        {"name": "TANG JIANHONG", "note": "(SCAM ONLINE)"},
        {"name": "CAO XING", "note": "(SCAM ONLINE)"},
        {"name": "YAN ZHIPENG", "note": "(SCAM ONLINE)"},
        {"name": "LI JIN", "note": "(SCAM ONLINE)"},
        {"name": "TAO YUYUAN", "note": "(SCAM ONLINE)"},
        {"name": "MA ENSHAN", "note": "(SCAM ONLINE)"},
        {"name": "WU FENGTING", "note": "(SCAM ONLINE)"},
        {"name": "SONG HEBIN", "note": "(SCAM ONLINE)"},
        {"name": "JIN DAIYING", "note": "(SCAM ONLINE)"},
        {"name": "WU JINFENG", "note": "(SCAM ONLINE)"},
        {"name": "LAN QI", "note": "(SCAM ONLINE)"},
        {"name": "PENG YUEYUN", "note": "(SCAM ONLINE)"},
        {"name": "DENG XU", "note": "(SCAM ONLINE)"},
        {"name": "NOVEL ANDRIANSGAH", "note": "(SCAM ONLINE)"},
        {"name": "MUHAMMAD RAMADHONI", "note": "(SCAM ONLINE)"},
        {"name": "AGUS", "note": "(SCAM ONLINE)"},
        {"name": "BUDI SUPRIYONO", "note": "(SCAM ONLINE)"},
        {"name": "ARI RAMADHAN", "note": "(SCAM ONLINE)"},
        {"name": "DENNY SHERGIN PANYALA", "note": "(SCAM ONLINE)"},
        {"name": "YOGA ANDIKA", "note": "(SCAM ONLINE)"},
        {"name": "ANDRIAN MAULANA", "note": "(SCAM ONLINE)"},
        {"name": "ANDY SYAHPUTRA", "note": "(SCAM ONLINE)"},
        {"name": "FIARV HAIKHRI", "note": "(SCAM ONLINE)"},
        {"name": "DENI", "note": "(SCAM ONLINE)"},
        {"name": "MARTHIN SIHOMBING", "note": "(SCAM ONLINE)"},
        {"name": "TARMONO PRAJOGO", "note": "(SCAM ONLINE)"},
        {"name": "DUAD SEPTIAN SIHOMBING", "note": "(SCAM ONLINE)"},
        {"name": "HAIIZH WIRAKUFUMA", "note": "(SCAM ONLINE)"},
        {"name": "BOY PRASISCO LAOLI", "note": "(SCAM ONLINE)"},
        {"name": "GUALBERTUS SURYANTO", "note": "(SCAM ONLINE)"},
        {"name": "MUHAMMAD KRISNADI", "note": "(SCAM ONLINE)"},
        {"name": "CHANDRA KIRANA", "note": "(SCAM ONLINE)"},
        {"name": "RESTU MAULANA", "note": "(SCAM ONLINE)"},
        {"name": "ACHNAD SHAUES", "note": "(SCAM ONLINE)"},
        {"name": "ANGGA RESTA ERLANGGA", "note": "(SCAM ONLINE)"},
        {"name": "AHMAD LATIEF", "note": "(SCAM ONLINE)"},
        {"name": "ADIYA IRWANSYAH", "note": "(SCAM ONLINE)"},
        {"name": "MUHAMMAD RISZKI", "note": "(SCAM ONLINE)"},
        {"name": "MUHAMMAD DHARAMAWANSYAN", "note": "(SCAM ONLINE)"},
        {"name": "AGUM M HIDAYAT", "note": "(SCAM ONLINE)"},
        {"name": "RIDHO JUSTISA DJAFAR", "note": "(SCAM ONLINE)"},
        {"name": "KENNETH ERIC RIVALDO SUPIT", "note": "(SCAM ONLINE)"},
        {"name": "ROINALDY RIZKY JOHSUA", "note": "(SCAM ONLINE)"},
        {"name": "RAFI DWI RAHMAT", "note": "(SCAM ONLINE)"},
        {"name": "FAHRIANSYAN", "note": "(SCAM ONLINE)"},
        {"name": "JAKA GALUH PAMUNGKAS", "note": "(SCAM ONLINE)"},
        {"name": "KARIM RAMADHAN", "note": "(SCAM ONLINE)"},
        {"name": "GHILMAN FAIZ", "note": "(SCAM ONLINE)"},
        {"name": "ANDRE TRI PUTRA SIMAMORA", "note": "(SCAM ONLINE)"},
        {"name": "MAULANA IKHSAN SIPAMUTAR", "note": "(SCAM ONLINE)"},
        {"name": "MIYA WASIM ALI", "note": "(SCAM ONLINE)"},
        {"name": "JAKA PRASTYA", "note": "(SCAM ONLINE)"},
        {"name": "FAZLIN AL MUTTAQIN", "note": "(SCAM ONLINE)"},
        {"name": "ANGGA PANDAPOTAN MANURUNG", "note": "(SCAM ONLINE)"},
        {"name": "ANTOSA", "note": "(SCAM ONLINE)"},
        {"name": "GUNAWAN OCTAVIANUS", "note": "(SCAM ONLINE)"},
        {"name": "PAHRUL ROJI", "note": "(SCAM ONLINE)"},
        {"name": "SURYA TRI HARLANDA", "note": "(SCAM ONLINE)"},
        {"name": "MULYANTO TJIA", "note": "(SCAM ONLINE)"},
        {"name": "ARDIANUS PSIANTURI", "note": "(SCAM ONLINE)"},
        {"name": "BOY ANGGAIAWAN", "note": "(SCAM ONLINE)"},
        {"name": "YONI FAMASTA PUTRA", "note": "(SCAM ONLINE)"},
        {"name": "YULULYA ZAKI", "note": "(SCAM ONLINE)"},
        {"name": "LEONARDO SITINJAK", "note": "(SCAM ONLINE)"},
        {"name": "SANDI AFFRIANDI", "note": "(SCAM ONLINE)"},
        {"name": "MUHAMMAD AQILAH RIFQI NASUTION", "note": "(SCAM ONLINE)"},
        {"name": "KHAIRUL AFRIANSAH", "note": "(SCAM ONLINE)"},
        {"name": "DIAN RAHMAN", "note": "(SCAM ONLINE)"},
        {"name": "DUNCAN WILLIAM", "note": "(SCAM ONLINE)"},
        {"name": "BAGUS PERWIRA", "note": "(SCAM ONLINE)"},
        {"name": "TRI EKA DARMA ANGGARA", "note": "(SCAM ONLINE)"},
        {"name": "FERY KURNIWAN", "note": "(SCAM ONLINE)"},
        {"name": "NAYA SYAFITRT DEWI", "note": "(SCAM ONLINE)"},
        {"name": "YOSA MIUENIA", "note": "(SCAM ONLINE)"},
        {"name": "KRIDA MIRANTIH DEWI", "note": "(SCAM ONLINE)"},
        {"name": "STEVANI PUSUNG", "note": "(SCAM ONLINE)"},
        {"name": "BEUA KUPNIA DWA YAPUTRI", "note": "(SCAM ONLINE)"},
        {"name": "JEISI SAHOA", "note": "(SCAM ONLINE)"},
        {"name": "DESRI NATALIA", "note": "(SCAM ONLINE)"},
        {"name": "VALENCIA JOANNA AMIE", "note": "(SCAM ONLINE)"},
        {"name": "LUTFATUNISA", "note": "(SCAM ONLINE)"},
        {"name": "DEWI OKTAVIANI", "note": "(SCAM ONLINE)"},
        {"name": "NANCY NOVELIA TASIAM", "note": "(SCAM ONLINE)"},
        {"name": "AGNES MANDAGZ", "note": "(SCAM ONLINE)"},
        {"name": "NINA ANDRI ANINGSIH", "note": "(SCAM ONLINE)"},
        {"name": "========================", "SCAMMMMMMMM-PHEAROMLIST": "=========================="},
        {"name": "========================", "SCAMMMMMMMM-9LIST": "=========================="},
        {"name": "LYU CONG", "note": "(SCAM ONLINE)"},
        {"name": "ZHOU BING", "note": "(SCAM ONLINE)"},
        {"name": "LV CHENGZONG", "note": "(SCAM ONLINE)"},
        {"name": "MO FEILONG", "note": "(SCAM ONLINE)"},
        {"name": "ZHU TENGUH", "note": "(SCAM ONLINE)"},
        {"name": "XIE YANXIAN", "note": "(SCAM ONLINE)"},
        {"name": "ZHANG FEI", "note": "(SCAM ONLINE)"},
        {"name": "LIU KUN", "note": "(SCAM ONLINE)"},
        {"name": "RAN LE", "note": "(SCAM ONLINE)"},
        {"name": "RIAN PADU", "note": "(SCAM ONLINE)"},
        {"name": "SYAPPUTR", "note": "(SCAM ONLINE)"},
        {"name": "DENI APRIYANTO", "note": "(SCAM ONLINE)"},
        {"name": "ROCKY RAMDONI", "note": "(SCAM ONLINE)"},
        {"name": "PUTRA INDRA HAMDALLAH DANU", "note": "(SCAM ONLINE)"},
        {"name": "ALFARIZI", "note": "(SCAM ONLINE)"},
        {"name": "RIDHO KURNIAWAN", "note": "(SCAM ONLINE)"},
        {"name": "MUHSININ", "note": "(SCAM ONLINE)"},
        {"name": "MAGRIBI MUHAMMAD NANDA", "note": "(SCAM ONLINE)"},
        {"name": "KOESRANDIKA MUHAMMAD", "note": "(SCAM ONLINE)"},
        {"name": "MUHAMMAD FAISAL", "note": "(SCAM ONLINE)"},
        {"name": "MULYANA AGUNG", "note": "(SCAM ONLINE)"},
        {"name": "SAPUTRA RIFKY", "note": "(SCAM ONLINE)"},
        {"name": "PURNAMA VICKY AKBAR", "note": "(SCAM ONLINE)"},
        {"name": "RUKMANA FERDY ARDIANSYAH", "note": "(SCAM ONLINE)"},
        {"name": "REZA MUHAMMAD", "note": "(SCAM ONLINE)"},
        {"name": "APRIYANDI RIKI", "note": "(SCAM ONLINE)"},
        {"name": "ADITYA ARSHEL", "note": "(SCAM ONLINE)"},
        {"name": "RAHMAN MUHAMMAD MITTAHUL", "note": "(SCAM ONLINE)"},
        {"name": "LANDI PAUT", "note": "(SCAM ONLINE)"},
        {"name": "ANDRIANSYAH MUHAMMAD", "note": "(SCAM ONLINE)"},
        {"name": "RUKI", "note": "(SCAM ONLINE)"},
        {"name": "RABDANI", "note": "(SCAM ONLINE)"},
        {"name": "ASRIZHAL SEPTIAN", "note": "(SCAM ONLINE)"},
        {"name": "ANANDA MUHAMMAD RIZKI", "note": "(SCAM ONLINE)"},
        {"name": "BAGAS ARIF WIBOWO", "note": "(SCAM ONLINE)"},
        {"name": "CHRISTIAN APRINAIATA", "note": "(SCAM ONLINE)"},
        {"name": "RIFHI SYAHPOTRA", "note": "(SCAM ONLINE)"},
        {"name": "YUDA LESMANA", "note": "(SCAM ONLINE)"},
        {"name": "NA DIA", "note": "(SCAM ONLINE)"},
        {"name": "AINA NUR", "note": "(SCAM ONLINE)"},
        {"name": "AUDINA MIA", "note": "(SCAM ONLINE)"},
        {"name": "SULISTYA NOVA", "note": "(SCAM ONLINE)"},
        {"name": "KHOERIRIS SITI", "note": "(SCAM ONLINE)"},
        {"name": "SARTIKA SITI", "note": "(SCAM ONLINE)"},
        {"name": "GULO ERLINA", "note": "(SCAM ONLINE)"},
        {"name": "MIRA DEWI", "note": "(SCAM ONLINE)"},
        {"name": "FARADILLA REGINA", "note": "(SCAM ONLINE)"},
        {"name": "MIRANDA AUDRY YUSTIRA", "note": "(SCAM ONLINE)"},
        {"name": "KRISTIANI DHEINA", "note": "(SCAM ONLINE)"},
        {"name": "MURCK HORIFAH", "note": "(SCAM ONLINE)"},
        {"name": "AMNISA RAHMAT LANA", "note": "(SCAM ONLINE)"},
        {"name": "ARIMBI NOVIA", "note": "(SCAM ONLINE)"},
        {"name": "MIFTAHUUANAH OSSY", "note": "(SCAM ONLINE)"},
        {"name": "SUNARTI SITI", "note": "(SCAM ONLINE)"},
        {"name": "TRISPRATIWI ISTIANA DIAN", "note": "(SCAM ONLINE)"},
        {"name": "ARIANDA", "note": "(SCAM ONLINE)"},
        {"name": "KABITA SHRESTHA", "note": "(SCAM ONLINE)"},
        {"name": "KUMARI BIMALA K C BHUSAL", "note": "(SCAM ONLINE)"},
        {"name": "TARIQ AMNA", "note": "(SCAM ONLINE)"},
        {"name": "NGUYEN THI THUY TRANG", "note": "(SCAM ONLINE)"},
        {"name": "NGO THU HI-JONG", "note": "(SCAM ONLINE)"},
        {"name": "WANG HUA", "note": "(SCAM ONLINE)"},
        {"name": "CAO YUJIE", "note": "(SCAM ONLINE)"},
        {"name": "BAI SHANSHAN", "note": "(SCAM ONLINE)"},
        {"name": "TIARA CANDRA MEGA", "note": "(SCAM ONLINE)"},
        {"name": "AFRIZAL SAMSUL", "note": "(SCAM ONLINE)"},
        {"name": "NURBAID EKO", "note": "(SCAM ONLINE)"},
        {"name": "KHAIRUL AMZI", "note": "(SCAM ONLINE)"},
        {"name": "RENDY ALPARLDO", "note": "(SCAM ONLINE)"},
        {"name": "FAJRI MUHAMMAD FADILAH", "note": "(SCAM ONLINE)"},
        {"name": "BAFADAL ILHAM", "note": "(SCAM ONLINE)"},
        {"name": "MARCELUNO uNGGA", "note": "(SCAM ONLINE)"},
        {"name": "SAPUTRA DIMAS APRILUAN", "note": "(SCAM ONLINE)"},
        {"name": "KUSUMA ARSA RIVA!", "note": "(SCAM ONLINE)"},
        {"name": "UCU NURGONI", "note": "(SCAM ONLINE)"},
        {"name": "QASIM MUHAMMAD BILAL", "note": "(SCAM ONLINE)"},
        {"name": "WAHID NIKO IRFAN", "note": "(SCAM ONLINE)"},
        {"name": "PUTRA ALFINCNUR FANI", "note": "(SCAM ONLINE)"},
        {"name": "EGI", "note": "(SCAM ONLINE)"},
        {"name": "FIRMANSYAH TEGUH ADI", "note": "(SCAM ONLINE)"},
        {"name": "CAHYADI AHMAD ZULFAHMI", "note": "(SCAM ONLINE)"},
        {"name": "HILMAWAN ANDRI", "note": "(SCAM ONLINE)"},
        {"name": "REZA AGUNG WIJAYA", "note": "(SCAM ONLINE)"},
        {"name": "KUSUMA FAJRI MAULANA", "note": "(SCAM ONLINE)"},
        {"name": "DANI MUHAMAD", "note": "(SCAM ONLINE)"},
        {"name": "KURNIAWAN SENDI", "note": "(SCAM ONLINE)"},
        {"name": "ARDIANSYAH", "note": "(SCAM ONLINE)"},
        {"name": "KHAFI AHMAD", "note": "(SCAM ONLINE)"},
        {"name": "CHANDRA PAJIDAN FASHA", "note": "(SCAM ONLINE)"},
        {"name": "PUTRA RAKA HERMAWAN", "note": "(SCAM ONLINE)"},
        {"name": "MAUI-ANA MUHAMAD ILYAS", "note": "(SCAM ONLINE)"},
        {"name": "AZEEZ ABEEB AYOBAMI", "note": "(SCAM ONLINE)"},
        {"name": "ADEGOKE IBRAHIM DAMILOLA", "note": "(SCAM ONLINE)"},
        {"name": "SHAH ATHAR", "note": "(SCAM ONLINE)"},
        {"name": "AWAIS MUHAMMAD", "note": "(SCAM ONLINE)"},
        {"name": "MUHAMMAD AWAIS", "note": "(SCAM ONLINE)"},
        {"name": "SHAHZAD ALAM", "note": "(SCAM ONLINE)"},
        {"name": "GULSAR", "note": "(SCAM ONLINE)"},
        {"name": "SAVEJ", "note": "(SCAM ONLINE)"},
        {"name": "Al-AM MOHAMMADNAHID", "note": "(SCAM ONLINE)"},
        {"name": "HAQUE MOHAMMADMINHAJUL", "note": "(SCAM ONLINE)"},
        {"name": "MOHAMMAD ASRARALAM", "note": "(SCAM ONLINE)"},
        {"name": "WANG JINHO", "note": "(SCAM ONLINE)"},
        {"name": "LAN JINGQIU", "note": "(SCAM ONLINE)"},
        {"name": "ZHOU SHUAIUN", "note": "(SCAM ONLINE)"},
        {"name": "FENG RUOFEI", "note": "(SCAM ONLINE)"},
        {"name": "SU FACHENG", "note": "(SCAM ONLINE)"},
        {"name": "DENG ZHENYU", "note": "(SCAM ONLINE)"},
        {"name": "NI ZHENG", "note": "(SCAM ONLINE)"},
        {"name": "XIE BIN", "note": "(SCAM ONLINE)"},
        {"name": "LI DONGKUI", "note": "(SCAM ONLINE)"},
        {"name": "LI JIAFU", "note": "(SCAM ONLINE)"},
        {"name": "WAN XIANG", "note": "(SCAM ONLINE)"},
        {"name": "ZHAO ZHENGQUAN", "note": "(SCAM ONLINE)"},
        {"name": "ZHOU SAOFENG", "note": "(SCAM ONLINE)"},
        {"name": "WU BAO", "note": "(SCAM ONLINE)"},
        {"name": "HAN JUNYAO", "note": "(SCAM ONLINE)"},
        {"name": "CHEN SIBIN", "note": "(SCAM ONLINE)"},
        {"name": "ZHENG JIE", "note": "(SCAM ONLINE)"},
        {"name": "TANG PENG", "note": "(SCAM ONLINE)"},
        {"name": "LIU QINGBO", "note": "(SCAM ONLINE)"},
        {"name": "YAO FEI", "note": "(SCAM ONLINE)"},
        {"name": "ANG YIJIAN", "note": "(SCAM ONLINE)"},
        {"name": "QIU HAIXIAO", "note": "(SCAM ONLINE)"},
        {"name": "WANG GUIBIN", "note": "(SCAM ONLINE)"},
        {"name": "XU QIANG", "note": "(SCAM ONLINE)"},
        {"name": "CHEN XIANG", "note": "(SCAM ONLINE)"},
        {"name": "HUANG Ll", "note": "(SCAM ONLINE)"},
        {"name": "FENG HAO", "note": "(SCAM ONLINE)"},
        {"name": "WANG JIEJIE", "note": "(SCAM ONLINE)"},
        {"name": "TIAN CHAO", "note": "(SCAM ONLINE)"},
        {"name": "YANG ZHUDE", "note": "(SCAM ONLINE)"},
        {"name": "WANG XIEGANG", "note": "(SCAM ONLINE)"},
        {"name": "XIAO SHIBING", "note": "(SCAM ONLINE)"},
        {"name": "LIANG TAO", "note": "(SCAM ONLINE)"},
        {"name": "DENG HAITAO", "note": "(SCAM ONLINE)"},
        {"name": "CAO ZHIHAO", "note": "(SCAM ONLINE)"},
        {"name": "XIAO YAOOIU", "note": "(SCAM ONLINE)"},
        {"name": "LI HUQUANG", "note": "(SCAM ONLINE)"},
        {"name": "WANG DI GIANG", "note": "(SCAM ONLINE)"},
        {"name": "MDERFAT GUUMAM", "note": "(SCAM ONLINE)"},
        {"name": "SA HIL", "note": "(SCAM ONLINE)"},
        {"name": "THAKUR PRITAM KUMAR", "note": "(SCAM ONLINE)"},
        {"name": "REYAZ EHSAN", "note": "(SCAM ONLINE)"},
        {"name": "FAI SAL", "note": "(SCAM ONLINE)"},
        {"name": "AASHISH BC", "note": "(SCAM ONLINE)"},
        {"name": "PRAJWAL MAGRATI", "note": "(SCAM ONLINE)"},
        {"name": "BHIM RAJ GURUNG", "note": "(SCAM ONLINE)"},
        {"name": "BAL BAHADUR BHAT CHHETRI", "note": "(SCAM ONLINE)"},
        {"name": "MANIK SHIWA", "note": "(SCAM ONLINE)"},
        {"name": "ARUN KC", "note": "(SCAM ONLINE)"},
        {"name": "AKASH TAMANG", "note": "(SCAM ONLINE)"},
        {"name": "ZODDERMD KOBIRHASAN", "note": "(SCAM ONLINE)"},
        {"name": "RAHNAN ATIKUR", "note": "(SCAM ONLINE)"},
        {"name": "MUKHARJEE TANMAI", "note": "(SCAM ONLINE)"},
        {"name": "HOSSAIN RIPON", "note": "(SCAM ONLINE)"},
        {"name": "AGUSTIN DWI AUUA", "note": "(SCAM ONLINE)"},
        {"name": "AGUSTIARA SHAKILA", "note": "(SCAM ONLINE)"},
        {"name": "ANINDA RAVINA", "note": "(SCAM ONLINE)"},
        {"name": "PURNAMA TIARA AGUSTIN", "note": "(SCAM ONLINE)"},
        {"name": "WITA ADINDA RAHMA", "note": "(SCAM ONLINE)"},
        {"name": "PANGARIBUAN MONIKA MEILANY", "note": "(SCAM ONLINE)"},
        {"name": "PATAMA PUTRI", "note": "(SCAM ONLINE)"},
        {"name": "HER VITA", "note": "(SCAM ONLINE)"},
        {"name": "JUNIAR ASTRID NURSILANATI", "note": "(SCAM ONLINE)"},
        {"name": "SHELIAWATI FUTRI", "note": "(SCAM ONLINE)"},
        {"name": "SYAHRIAN KHAIRANI", "note": "(SCAM ONLINE)"},
        {"name": "ROSITA INTAN", "note": "(SCAM ONLINE)"},
        {"name": "FAUZIAH NIMAS", "note": "(SCAM ONLINE)"},
        {"name": "RACHMAWATI EVA", "note": "(SCAM ONLINE)"},
        {"name": "WIJAYA ANGELIQUE", "note": "(SCAM ONLINE)"},
        {"name": "ENDARYANSYAH HERVIANTI", "note": "(SCAM ONLINE)"},
        {"name": "KURNIA ESA", "note": "(SCAM ONLINE)"},
        {"name": "KOMALASARI ERNA", "note": "(SCAM ONLINE)"},
        {"name": "SEP TIANJANI", "note": "(SCAM ONLINE)"},
        {"name": "SARI RIA PERMATA", "note": "(SCAM ONLINE)"},
        {"name": "FITRIA HANDAYANI", "note": "(SCAM ONLINE)"},
        {"name": "ANANDRA KARININA DELI", "note": "(SCAM ONLINE)"},
        {"name": "AIMAN AIFIT", "note": "(SCAM ONLINE)"},
        {"name": "SUPRI HARTONO", "note": "(SCAM ONLINE)"},
        {"name": "TONI LIM", "note": "(SCAM ONLINE)"},
        {"name": "MUHAMMAD ARMANDA NASUTION", "note": "(SCAM ONLINE)"},
        {"name": "SURYA SANJAYA", "note": "(SCAM ONLINE)"},
        {"name": "PUTRA RIZKI FERNANDO", "note": "(SCAM ONLINE)"},
        {"name": "PRATAMA ALDY TEGAR", "note": "(SCAM ONLINE)"},
        {"name": "ARIF", "note": "(SCAM ONLINE)"},
        {"name": "HAKIKI SURYA", "note": "(SCAM ONLINE)"},
        {"name": "MULYANA DICKY", "note": "(SCAM ONLINE)"},
        {"name": "FATHURRAHMAN MUHAMMAD", "note": "(SCAM ONLINE)"},
        {"name": "PRASSTIO WAHYU", "note": "(SCAM ONLINE)"},
        {"name": "BUANDPA AREMBI ULPA", "note": "(SCAM ONLINE)"},
        {"name": "BRAMANTIORO BAGAS SATRIO", "note": "(SCAM ONLINE)"},
        {"name": "JOFADLY RAFLY", "note": "(SCAM ONLINE)"},
        {"name": "H AGAUF ISNAN", "note": "(SCAM ONLINE)"},
        {"name": "WARUWU AGUSMAN JAYA", "note": "(SCAM ONLINE)"},
        {"name": "SITORUS DANIEL", "note": "(SCAM ONLINE)"},
        {"name": "MAIL SAMUEL YOHANES", "note": "(SCAM ONLINE)"},
        {"name": "E LIND", "note": "(SCAM ONLINE)"},
        {"name": "MUHAMAD ROBBY PUTRA", "note": "(SCAM ONLINE)"},
        {"name": "WAHID ABD", "note": "(SCAM ONLINE)"},
        {"name": "PADILAH ILHAM", "note": "(SCAM ONLINE)"},
        {"name": "JUANDA WILLY", "note": "(SCAM ONLINE)"},
        {"name": "RIJAYA DESTA", "note": "(SCAM ONLINE)"},
        {"name": "RISWANTO ANTO", "note": "(SCAM ONLINE)"},
        {"name": "YOGO HENSEN FRANS", "note": "(SCAM ONLINE)"},
        {"name": "SUKRI AKMAL", "note": "(SCAM ONLINE)"},
        {"name": "KUMAR PIJAY", "note": "(SCAM ONLINE)"},
        {"name": "WIBOWO ALBERT", "note": "(SCAM ONLINE)"},
        {"name": "KRISWARDANA DENI", "note": "(SCAM ONLINE)"},
        {"name": "PUTRA M FAI-ADIN", "note": "(SCAM ONLINE)"},
        {"name": "SAPUTRA INDRA", "note": "(SCAM ONLINE)"},
        {"name": "ADIPERBAWA DIMAS NHARAYA", "note": "(SCAM ONLINE)"},
        {"name": "RU DI", "note": "(SCAM ONLINE)"},
        {"name": "VIKKI EKARAMDHANI", "note": "(SCAM ONLINE)"},
        {"name": "SAPUTRA ANGGA", "note": "(SCAM ONLINE)"},
        {"name": "RAMDANI DADAN", "note": "(SCAM ONLINE)"},
        {"name": "HOANG VAN TUAN", "note": "(SCAM ONLINE)"},
        {"name": "PHAM GIA UNH", "note": "(SCAM ONLINE)"},
        {"name": "TRAN TIEN HY", "note": "(SCAM ONLINE)"},
        {"name": "TANG GIA HUY", "note": "(SCAM ONLINE)"},
        {"name": "WANG XIAOJUN", "note": "(SCAM ONLINE)"},
        {"name": "ZHENG BIN", "note": "(SCAM ONLINE)"},
        {"name": "HUANG XUDONG", "note": "(SCAM ONLINE)"},
        {"name": "YANG YUANCAI", "note": "(SCAM ONLINE)"},
        {"name": "UN WEI", "note": "(SCAM ONLINE)"},
        {"name": "ZHANG HAO", "note": "(SCAM ONLINE)"},
        {"name": "QING JINGUNG", "note": "(SCAM ONLINE)"},
        {"name": "GONG JIANHAO", "note": "(SCAM ONLINE)"},
        {"name": "LI SHAOUNG", "note": "(SCAM ONLINE)"},
        {"name": "XIAO SHUNSHENG", "note": "(SCAM ONLINE)"},
        {"name": "WU FENG", "note": "(SCAM ONLINE)"},
        {"name": "YANG BO", "note": "(SCAM ONLINE)"},
        {"name": "SU ZHENGDONG", "note": "(SCAM ONLINE)"},
        {"name": "MA JIAWU", "note": "(SCAM ONLINE)"},
        {"name": "GUO JUNJIE", "note": "(SCAM ONLINE)"},
        {"name": "WANG PEIJIE", "note": "(SCAM ONLINE)"},
        {"name": "XIONG XIANG", "note": "(SCAM ONLINE)"},
        {"name": "UANG CHENGQIANG", "note": "(SCAM ONLINE)"},
        {"name": "YU YANGYANG", "note": "(SCAM ONLINE)"},
        {"name": "TAN QINGCHAN", "note": "(SCAM ONLINE)"},
        {"name": "YANG YANG", "note": "(SCAM ONLINE)"},
        {"name": "MENG UNGHUI", "note": "(SCAM ONLINE)"},
        {"name": "WANG XIONG", "note": "(SCAM ONLINE)"},
        {"name": "HUANG YAOTING", "note": "(SCAM ONLINE)"},
        {"name": "CHEN MING", "note": "(SCAM ONLINE)"},
        {"name": "LUO JINHONG", "note": "(SCAM ONLINE)"},
        {"name": "YANG JONGHAO", "note": "(SCAM ONLINE)"},
        {"name": "CHEN ZEKAI", "note": "(SCAM ONLINE)"},
        {"name": "HUANG YU", "note": "(SCAM ONLINE)"},
        {"name": "LI JANGHONG", "note": "(SCAM ONLINE)"},
        {"name": "DENG XUJING", "note": "(SCAM ONLINE)"},
        {"name": "YUAN YU", "note": "(SCAM ONLINE)"},
        {"name": "PAGE8", "note": "(SCAM ONLINE)"},
        {"name": "XIAO MING", "note": "(SCAM ONLINE)"},
        {"name": "SU YUN", "note": "(SCAM ONLINE)"},
        {"name": "CHEN XUBO", "note": "(SCAM ONLINE)"},
        {"name": "LU LISAN", "note": "(SCAM ONLINE)"},
        {"name": "ZENG HI-JILONG", "note": "(SCAM ONLINE)"},
        {"name": "HI-JO GIANG", "note": "(SCAM ONLINE)"},
        {"name": "SUN BAOSHENG", "note": "(SCAM ONLINE)"},
        {"name": "RAN QINGFEI", "note": "(SCAM ONLINE)"},
        {"name": "FU HAINAN", "note": "(SCAM ONLINE)"},
        {"name": "MA JIAHAO", "note": "(SCAM ONLINE)"},
        {"name": "CHEN FENG", "note": "(SCAM ONLINE)"},
        {"name": "CHEN MINGHAN", "note": "(SCAM ONLINE)"},
        {"name": "WANG YAN", "note": "(SCAM ONLINE)"},
        {"name": "U HANBIAO", "note": "(SCAM ONLINE)"},
        {"name": "WANG YINA", "note": "(SCAM ONLINE)"},
        {"name": "ZHAO YONGFU", "note": "(SCAM ONLINE)"},
        {"name": "ZHANG BING", "note": "(SCAM ONLINE)"},
        {"name": "ZHOU YANG", "note": "(SCAM ONLINE)"},
        {"name": "HU JIAN", "note": "(SCAM ONLINE)"},
        {"name": "TIAN QIBING", "note": "(SCAM ONLINE)"},
        {"name": "WANG HUI", "note": "(SCAM ONLINE)"},
        {"name": "HONG XIAOHAN", "note": "(SCAM ONLINE)"},
        {"name": "FANG JIADONG", "note": "(SCAM ONLINE)"},
        {"name": "PENG BING", "note": "(SCAM ONLINE)"},
        {"name": "GUO HIJ", "note": "(SCAM ONLINE)"},
        {"name": "Y WENXING", "note": "(SCAM ONLINE)"},
        {"name": "FANG JIWEI", "note": "(SCAM ONLINE)"},
        {"name": "YANG XINGSUN", "note": "(SCAM ONLINE)"},
        {"name": "TAO FANGJING", "note": "(SCAM ONLINE)"},
        {"name": "RONG JIANG", "note": "(SCAM ONLINE)"},
        {"name": "VI DUC HUYNH", "note": "(SCAM ONLINE)"},
        {"name": "PHAM THE DUY", "note": "(SCAM ONLINE)"},
        {"name": "MAI LE DO NHUAN", "note": "(SCAM ONLINE)"},
        {"name": "TRAN NHAT BAO", "note": "(SCAM ONLINE)"},
        {"name": "TRUONG DUY ANH", "note": "(SCAM ONLINE)"},
        {"name": "TRAN HUYNH HANG", "note": "(SCAM ONLINE)"},
        {"name": "BUI VAN", "note": "(SCAM ONLINE)"},
        {"name": "BUI WY TIEN", "note": "(SCAM ONLINE)"},
        {"name": "NGUYEN TRINAM ANH", "note": "(SCAM ONLINE)"},
        {"name": "LUONG PHI-JC HAU", "note": "(SCAM ONLINE)"},
        {"name": "LOTHAI HOP", "note": "(SCAM ONLINE)"},
        {"name": "PHAM VAN TOAN", "note": "(SCAM ONLINE)"},
        {"name": "BUI VAN MINH", "note": "(SCAM ONLINE)"},
        {"name": "LO VAN DUNG", "note": "(SCAM ONLINE)"},
        {"name": "HOANG TRUNG HAU", "note": "(SCAM ONLINE)"},
        {"name": "DOAN PHI HUNG", "note": "(SCAM ONLINE)"},
        {"name": "EJ7214796", "note": "(SCAM ONLINE)"},
        {"name": "EP0717076", "note": "(SCAM ONLINE)"},
        {"name": "T01952985", "note": "(SCAM ONLINE)"},
        {"name": "E8861908", "note": "(SCAM ONLINE)"},
        {"name": "E2290824", "note": "(SCAM ONLINE)"},
        {"name": "E9677873", "note": "(SCAM ONLINE)"},
        {"name": "E9745047", "note": "(SCAM ONLINE)"},
        {"name": "E7060553", "note": "(SCAM ONLINE)"},
        {"name": "E9865183", "note": "(SCAM ONLINE)"},
        {"name": "E3348008", "note": "(SCAM ONLINE)"},
        {"name": "E9745066", "note": "(SCAM ONLINE)"},
        {"name": "E2692841", "note": "(SCAM ONLINE)"},
        {"name": "E7060972", "note": "(SCAM ONLINE)"},
        {"name": "E9865280", "note": "(SCAM ONLINE)"},
        {"name": "E8010429", "note": "(SCAM ONLINE)"},
        {"name": "E9865275", "note": "(SCAM ONLINE)"},
        {"name": "X8736567", "note": "(SCAM ONLINE)"},
        {"name": "E3472690", "note": "(SCAM ONLINE)"},
        {"name": "C9898572", "note": "(SCAM ONLINE)"},
        {"name": "E9745060", "note": "(SCAM ONLINE)"},
        {"name": "E3317397", "note": "(SCAM ONLINE)"},
        {"name": "X8741730", "note": "(SCAM ONLINE)"},
        {"name": "E9865477", "note": "(SCAM ONLINE)"},
        {"name": "E4269301", "note": "(SCAM ONLINE)"},
        {"name": "E0256796", "note": "(SCAM ONLINE)"},
        {"name": "X6750619", "note": "(SCAM ONLINE)"},
        {"name": "E6088935", "note": "(SCAM ONLINE)"},
        {"name": "X2374395", "note": "(SCAM ONLINE)"},
        {"name": "E7064586", "note": "(SCAM ONLINE)"},
        {"name": "E5182749", "note": "(SCAM ONLINE)"},
        {"name": "E9865248", "note": "(SCAM ONLINE)"},
        {"name": "E5252203", "note": "(SCAM ONLINE)"},
        {"name": "E9744966", "note": "(SCAM ONLINE)"},
        {"name": "E9164301", "note": "(SCAM ONLINE)"},
        {"name": "E8665383", "note": "(SCAM ONLINE)"},
        {"name": "GF7965691", "note": "(SCAM ONLINE)"},
        {"name": "E03981035", "note": "(SCAM ONLINE)"},
        {"name": "E2707145", "note": "(SCAM ONLINE)"},
        {"name": "X9444240", "note": "(SCAM ONLINE)"},
        {"name": "E9959629", "note": "(SCAM ONLINE)"},
        {"name": "X6575703", "note": "(SCAM ONLINE)"},
        {"name": "X5359612", "note": "(SCAM ONLINE)"},
        {"name": "E7064597", "note": "(SCAM ONLINE)"},
        {"name": "DC4854731", "note": "(SCAM ONLINE)"},
        {"name": "E1782552", "note": "(SCAM ONLINE)"},
        {"name": "X7626488", "note": "(SCAM ONLINE)"},
        {"name": "E1946854", "note": "(SCAM ONLINE)"},
        {"name": "E9744934", "note": "(SCAM ONLINE)"},
        {"name": "E0875549", "note": "(SCAM ONLINE)"},
        {"name": "E7064594", "note": "(SCAM ONLINE)"},
        {"name": "X4981055", "note": "(SCAM ONLINE)"},
        {"name": "X5361169", "note": "(SCAM ONLINE)"},
        {"name": "X2382734", "note": "(SCAM ONLINE)"},
        {"name": "E4075890", "note": "(SCAM ONLINE)"},
        {"name": "E5184223", "note": "(SCAM ONLINE)"},
        {"name": "E9865249", "note": "(SCAM ONLINE)"},
        {"name": "E5184188", "note": "(SCAM ONLINE)"},
        {"name": "B01441522", "note": "(SCAM ONLINE)"},
        {"name": "B03233765", "note": "(SCAM ONLINE)"},
        {"name": "UW5159841", "note": "(SCAM ONLINE)"},
        {"name": "AT1697302", "note": "(SCAM ONLINE)"},
        {"name": "T01543763", "note": "(SCAM ONLINE)"},
        {"name": "EF8400403", "note": "(SCAM ONLINE)"},
        {"name": "EP2484611", "note": "(SCAM ONLINE)"},
        {"name": "EM0532542", "note": "(SCAM ONLINE)"},
        {"name": "EG8457777", "note": "(SCAM ONLINE)"},
        {"name": "AD520629", "note": "(SCAM ONLINE)"},
        {"name": "A11836477", "note": "(SCAM ONLINE)"},
        {"name": "A01357083", "note": "(SCAM ONLINE)"},
        {"name": "X4955545", "note": "(SCAM ONLINE)"},
        {"name": "E7468152", "note": "(SCAM ONLINE)"},
        {"name": "E9745078", "note": "(SCAM ONLINE)"},
        {"name": "E0779545", "note": "(SCAM ONLINE)"},
        {"name": "E7332406", "note": "(SCAM ONLINE)"},
        {"name": "X6332567", "note": "(SCAM ONLINE)"},
        {"name": "E7337534", "note": "(SCAM ONLINE)"},
        {"name": "X7797028", "note": "(SCAM ONLINE)"},
        {"name": "X8285542", "note": "(SCAM ONLINE)"},
        {"name": "E9745128", "note": "(SCAM ONLINE)"},
        {"name": "E7922892", "note": "(SCAM ONLINE)"},
        {"name": "E9164425", "note": "(SCAM ONLINE)"},
        {"name": "E9744624", "note": "(SCAM ONLINE)"},
        {"name": "E0560408", "note": "(SCAM ONLINE)"},
        {"name": "E0256767", "note": "(SCAM ONLINE)"},
        {"name": "E0770761", "note": "(SCAM ONLINE)"},
        {"name": "E1127357", "note": "(SCAM ONLINE)"},
        {"name": "E0641371", "note": "(SCAM ONLINE)"},
        {"name": "E0641425", "note": "(SCAM ONLINE)"},
        {"name": "E9744623", "note": "(SCAM ONLINE)"},
        {"name": "E9745065", "note": "(SCAM ONLINE)"},
        {"name": "E7288947", "note": "(SCAM ONLINE)"},
        {"name": "X6663834", "note": "(SCAM ONLINE)"},
        {"name": "E9745048", "note": "(SCAM ONLINE)"},
        {"name": "E9865247", "note": "(SCAM ONLINE)"},
        {"name": "E4107941", "note": "(SCAM ONLINE)"},
        {"name": "E7827521", "note": "(SCAM ONLINE)"},
        {"name": "E9865478", "note": "(SCAM ONLINE)"},
        {"name": "E6025919", "note": "(SCAM ONLINE)"},
        {"name": "X8741726", "note": "(SCAM ONLINE)"},
        {"name": "X9448051", "note": "(SCAM ONLINE)"},
        {"name": "E9745293", "note": "(SCAM ONLINE)"},
        {"name": "E9745059", "note": "(SCAM ONLINE)"},
        {"name": "E9793325", "note": "(SCAM ONLINE)"},
        {"name": "E7336818", "note": "(SCAM ONLINE)"},
        {"name": "X5731076", "note": "(SCAM ONLINE)"},
        {"name": "E9745095", "note": "(SCAM ONLINE)"},
        {"name": "X7626481", "note": "(SCAM ONLINE)"},
        {"name": "E1528736", "note": "(SCAM ONLINE)"},
        {"name": "E6020903", "note": "(SCAM ONLINE)"},
        {"name": "E5806198", "note": "(SCAM ONLINE)"},
        {"name": "X6663899", "note": "(SCAM ONLINE)"},
        {"name": "X6663896", "note": "(SCAM ONLINE)"},
        {"name": "E2617378", "note": "(SCAM ONLINE)"},
        {"name": "E8665386", "note": "(SCAM ONLINE)"},
        {"name": "X7796739", "note": "(SCAM ONLINE)"},
        {"name": "E9744967", "note": "(SCAM ONLINE)"},
        {"name": "X7626776", "note": "(SCAM ONLINE)"},
        {"name": "X7626777", "note": "(SCAM ONLINE)"},
        {"name": "X8721963", "note": "(SCAM ONLINE)"},
        {"name": "E5605734", "note": "(SCAM ONLINE)"},
        {"name": "E9745049", "note": "(SCAM ONLINE)"},
        {"name": "E7059649", "note": "(SCAM ONLINE)"},
        {"name": "X2572024", "note": "(SCAM ONLINE)"},
        {"name": "EP0146518", "note": "(SCAM ONLINE)"},
        {"name": "EM0713175", "note": "(SCAM ONLINE)"},
        {"name": "EL2348830", "note": "(SCAM ONLINE)"},
        {"name": "EC2230300", "note": "(SCAM ONLINE)"},
        {"name": "EJ1880198", "note": "(SCAM ONLINE)"},
        {"name": "EF3241048", "note": "(SCAM ONLINE)"},
        {"name": "EP8053739", "note": "(SCAM ONLINE)"},
        {"name": "EL3452975", "note": "(SCAM ONLINE)"},
        {"name": "EP4820475", "note": "(SCAM ONLINE)"},
        {"name": "EM6940636", "note": "(SCAM ONLINE)"},
        {"name": "E05153652", "note": "(SCAM ONLINE)"},
        {"name": "P03587677", "note": "(SCAM ONLINE)"},
        {"name": "========================", "SCAMMMMMMMM-9LIST": "=========================="},
        {"name": "========================", "SCAMMMMMMMM": "=========================="},
        {"name": "SONG SHUAI", "note": "(EP8487503 SCAM ONLINE https://t.me/c/2101838153/29545)"},
        {"name": "EP8487503", "note": "(SONG SHUAI SCAM ONLINE https://t.me/c/2101838153/29545)"},
        {"name": "WENG SHENGFENG", "note": "( SCAM ONLINE https://t.me/c/2101838153/29537)"},
        {"name": "LIAO QUANWEI", "note": "( SCAM ONLINE https://t.me/c/2101838153/29537)"},
        {"name": "SHEN YUJIAN", "note": "(EC5872381 SCAM ONLINE https://t.me/c/2101838153/29544)"},
        {"name": "EC5872381", "note": "(SHEN YUJIAN SCAM ONLINE https://t.me/c/2101838153/29544)"},
        {"name": "========================", "SCAMMMMMMMM": "=========================="},
        {"name": "========================", "note": "=========================="},
        {"name": "RIAN DELON", "note": "ភ្ងៀវ CANCEL តែចេញកាត E5839832 SHV-SL893"},
        {"name": "E5839832", "note": "ភ្ងៀវ CANCEL តែចេញកាត RIAN DELON SHV-SL893"},
        {"name": "ZHANG BINGFENG", "note": "ភ្ងៀវ CANCEL តែចេញកាត EH8060462 SHV-SL915"},
        {"name": "EH8060462", "note": "ភ្ងៀវ CANCEL តែចេញកាត ZHANG BINGFENG SHV-SL915"},
        {"name": "QIN XIONG", "note": "ភ្ងៀវ CANCEL តែចេញកាត EH5069814 SHV-SDNT1382"},
        {"name": "EH5069814", "note": "ភ្ងៀវ CANCEL តែចេញកាត QIN XIONG SHV-SDNT1382"},
        {"name": "A2826369", "note": "ភ្ងៀវ CANCEL តែចេញកាត BEGENCHMYRADOV ARSLAN TAG-SO2457"},
        {"name": "BEGENCHMYRADOV ARSLAN", "note": "ភ្ងៀវ CANCEL តែចេញកាត A2826369 TAG-SO2457"},
        {"name": "EM1813092", "note": "ភ្ងៀវ CANCEL តែចេញកាត CHEN YIFEI S-PW-71"},
        {"name": "CHEN YIFEI", "note": "ភ្ងៀវ CANCEL តែចេញកាត EM1813092 S-PW-71"},
        {"name": "C8790208", "note": "ភ្ងៀវ CANCEL តែចេញកាត DAU THI TAM MT-3641"},
        {"name": "DAU THI TAM", "note": "ភ្ងៀវ CANCEL តែចេញកាត C8790208 MT-3641"},
        {"name": "EF9223905", "note": "ភ្ងៀវ CANCEL តែចេញកាត WANG JINDUI CBM-317 S-BAO-322"},
        {"name": "WANG JINDUI", "note": "ភ្ងៀវ CANCEL តែចេញកាត EF9223905 CBM-317 S-BAO-322"},
        {"name": "========================", "note": "=========================="},
        {"name": "ZACHARIASSEN DAG RUNE", "note": "(CCC574051 ជនជាតិ​​ Norwegian អ្នកកាសែត https://t.me/c/3854502836/254)"},
        {"name": "CCC574051", "note": "(ZACHARIASSEN DAG RUNE ជនជាតិ​​ Norwegian អ្នកកាសែត https://t.me/c/3854502836/254)"},
        {"name": "SIDENKO SERGEY", "note": "(550278660 ជនជាតិ​ Russian អ្នកកាសែត https://t.me/c/3854502836/156)"},
        {"name": "550278660", "note": "(SIDENKO SERGEY ជនជាតិ​ Russian អ្នកកាសែត https://t.me/c/3854502836/1564)"},
        {"name": "ZHANG YU", "note": "(EJ2571957 FAKE PASSPORT https://t.me/c/3854502836/355)"},
        {"name": "EJ2571957", "note": "(ZHANG YU FAKE PASSPORT https://t.me/c/3854502836/355)"},
        {"name": "ZHU NINGLI", "note": "(EJ8749889 FAKE PASSPORT https://t.me/c/3854502836/356)"},
        {"name": "EJ8749889", "note": "(ZHU NINGLI FAKE PASSPORT https://t.me/c/3854502836/356)"},
        {"name": "KARINA ESPERANZA ARGUETA PONCE", "note": "(B05401253 វើការងារអង្គការប https://t.me/c/3854502836/271)"},
        {"name": "B05401253", "note": "(KARINA ESPERANZA ARGUETA PONCE វើការងារអង្គការប https://t.me/c/3854502836/271)"},
        {"name": "WU ZHIYONG", "note": "(ER5168182 មើលគ្រុប ACELIDA សួរចែសិន 07/APR/2026)"},
        {"name": "ER5168182", "note": "(WU ZHIYONG មើលគ្រុប ACELIDA សួរចែសិន 07/APR/2026)"},
        {"name": "EJ9323105", "note": "(SUN WEIBING មើលគ្រុប ACELIDA សួរចែសិន 07/APR/2026)"},
        {"name": "SUN WEIBING", "note": "(EJ9323105 មើលគ្រុប ACELIDA សួរចែសិន 07/APR/2026)"},
        {"name": "EM7393452", "note": "(មើលគ្រុប ACELIDA សួរចែសិន)"},
        {"name": "EC7137542", "note": "(មើលគ្រុប ACELIDA សួរចែសិន)"},
        {"name": "EG7230166", "note": "(មើលគ្រុប ACELIDA សួរចែសិន)"},
        {"name": "HE DONGHUANG", "note": "(កាត់តកាត 2023 ដាក់ 2025 EK6910579 https://t.me/c/3875174011/146)"},
        {"name": "EK6910579", "note": "(កាត់តកាត 2023 ដាក់ 2025 HE DONGHUANG https://t.me/c/3875174011/146)"},
        {"name": "CHARLIE TIU HAY ANG", "note": "(ជាប់ទោស ATONG ANG https://t.me/c/3875174011/127)"},
        {"name": "ATONG ANG", "note": "(ជាប់ទោស CHARLIE TIU HAY ANG https://t.me/c/3875174011/127)"},
        {"name": "STANLEY", "note": "(ជាប់ទោស E0545397 https://t.me/c/3875174011/109)"},
        {"name": "E0545397", "note": "(ជាប់ទោស STANLEY https://t.me/c/3875174011/109)"},
        {"name": "LOO SHER WAI", "note": "(គេបញ្ចូលខុសទិន្នន័យ ចេញកាត2025 S-AC-02 A71230449 https://t.me/c/3875174011/93)"},
        {"name": "A71230449", "note": "(គេបញ្ចូលខុសទិន្នន័យ ចេញកាត2025 S-AC-02 LOO SHER WAI https://t.me/c/3875174011/93)"},
        {"name": "WANG LEI", "note": "(FAKE VISA SCAM ONLINE EK1934057 https://t.me/c/3875174011/5)"},
        {"name": "EK1934057", "note": "(FAKE VISA SCAM ONLINE WANG LEI https://t.me/c/3875174011/5)"},
        {"name": "ZHANG XIAOXU", "note": "(FAKE VISA)"},
        {"name": "HOSSEN MARUF", "note": "(ម្នាក់នេះកែលេខ ចេញចូល វីសាបង)"},
        {"name": "ABU SALMA", "note": "(CARD កាត់តបង (TNTO))"},
        {"name": "TU CHIH SHUN", "note": "(FAKE VISA)"},
        {"name": "WANG QI", "note": "(FAKE VISA)"},
        {"name": "EP3721214", "note": "(FAKE VISA)"},
        {"name": "DU GANG", "note": "(FAKE VISA)"},
        {"name": "CAO JIANLI", "note": "(FAKE VISA)"},
        {"name": "CHEN CUNZHI", "note": "(FAKE VISA)"},
        {"name": "CHU JIAJIA", "note": "(FAKE VISA)"},
        {"name": "FU WEI", "note": "(FAKE VISA)"},
        {"name": "GAO ZHI", "note": "(FAKE VISA)"},
        {"name": "HU YAJUN", "note": "(FAKE VISA)"},
        {"name": "LIU YUEYUAN", "note": "(FAKE VISA)"},
        {"name": "LAI YINGZHI", "note": "(FAKE VISA)"},
        {"name": "LIU LAICHUN", "note": "(FAKE VISA)"},
        {"name": "LIU XIAOBO", "note": "(FAKE VISA)"},
        {"name": "MA DINGCAI", "note": "(FAKE VISA)"},
        {"name": "ZHENG MAOQIANG", "note": "(FAKE VISA)"},
        {"name": "NING HAO", "note": "(FAKE VISA)"},
        {"name": "LIU DONGCAI", "note": "(FAKE VISA)"},
        {"name": "RENALDO MAULANA", "note": "(FAKE VISA)"},
        {"name": "SHAO YULIN", "note": "(FAKE VISA)"},
        {"name": "LAI ZHIHENG", "note": "(FAKE VISA)"},
        {"name": "WANG XIAORONG", "note": "(FAKE VISA)"},
        {"name": "WANG XINWEN", "note": "(FAKE VISA)"},
        {"name": "JI SHIGUO", "note": "(FAKE VISA)"},
        {"name": "YANG YUXIAO", "note": "(FAKE VISA)"},
        {"name": "ZHAO LIJUAN", "note": "(FAKE VISA)"},
        {"name": "ZENG XIONGFENG", "note": "(FAKE VISA)"},
        {"name": "ZHOU KUN", "note": "(FAKE VISA)"},
        {"name": "ZHAO HAIJUN", "note": "(FAKE VISA & SCAM ONLINE)"},
        {"name": "XU YOURAN", "note": "(FAKE VISA)"},
        {"name": "ZHU DANLING", "note": "(FAKE VISA)"},
        {"name": "ZHU JIANGHUA", "note": "(FAKE VISA)"},
        {"name": "WANG JIANGTAO", "note": "(FAKE VISA)"},
        {"name": "R5528525", "note": "BPH-1163 (FAKE VISA)"},
        {"name": "MANKARA THODI MOHAMMED ALTHAF", "note": "BPH-1163 (FAKE VISA)"}, 
        {"name": "========================", "សង្ស័យ": "=========================="},
        {"name": "EP9923396", "note": "សង្ស័យក្លែងក្លាយ FU MAODONG https://t.me/c/3604999601/22"},
        {"name": "FU MAODONG", "note": "សង្ស័យក្លែងក្លាយ EP9923396 https://t.me/c/3604999601/22"},
        {"name": "MK514378", "note": "សង្ស័យក្លែងក្លាយ KAR MAYE HLA https://t.me/c/3604999601/24"},
        {"name": "KAR MAYE HLA", "note": "សង្ស័យក្លែងក្លាយ MK514378 https://t.me/c/3604999601/24"},
        {"name": "A17030655", "note": "សង្ស័យក្លែងក្លាយ PAL SAJOL https://t.me/c/3604999601/26"},
        {"name": "PAL SAJOL", "note": "សង្ស័យក្លែងក្លាយ A17030655 https://t.me/c/3604999601/26"},
        {"name": "E2864813", "note": "សង្ស័យក្លែងក្លាយ HUSNI MUBAROG https://t.me/c/3604999601/51"},
        {"name": "HUSNI MUBAROG", "note": "សង្ស័យក្លែងក្លាយ E2864813 https://t.me/c/3604999601/51"},
        {"name": "EQ6427855", "note": "សង្ស័យក្លែងក្លាយ JI XIAOLING https://t.me/c/3604999601/39"},
        {"name": "JI XIAOLING", "note": "សង្ស័យក្លែងក្លាយ EQ6427855 https://t.me/c/3604999601/39"},
        {"name": "EJ1662995", "note": "សង្ស័យក្លែងក្លាយ JIANG DONGHUNG https://t.me/c/3604999601/28"},
        {"name": "JIANG DONGHUNG", "note": "សង្ស័យក្លែងក្លាយ EJ1662995 https://t.me/c/3604999601/28"},
        {"name": "R1811791", "note": "សង្ស័យក្លែងក្លាយ XING XIN https://t.me/c/3604999601/43"},
        {"name": "XING XIN", "note": "សង្ស័យក្លែងក្លាយ R1811791 https://t.me/c/3604999601/43"},
        {"name": "RV0162424", "note": "សង្ស័យក្លែងក្លាយ LIANG DONG https://t.me/c/3604999601/45"},
        {"name": "LIANG DONG", "note": "សង្ស័យក្លែងក្លាយ RV0162424 https://t.me/c/3604999601/45"},
        {"name": "========================", "សង្ស័យ": "=========================="},
        {"name": "CHEN ZHIQIN", "note": "គ្រឿងញៀន ហាមបញ្ចូល https://t.me/c/3675711084/9256/10773"},
        {"name": "WANG YINFU", "note": "គ្រឿងញៀន ហាមបញ្ចូល https://t.me/c/3675711084/9256/10773"},
        {"name": "YANG FUDE", "note": "គ្រឿងញៀន ហាមបញ្ចូល https://t.me/c/3675711084/9256/10773"},
        {"name": "TAN YANGYI", "note": "គ្រឿងញៀន ហាមបញ្ចូល https://t.me/c/3675711084/9256/10773"},
        {"name": "EM3527172", "note": "គ្រឿងញៀន ហាមបញ្ចូល XU HAO https://t.me/c/3675711084/9256/10774"},
        {"name": "XU HAO", "note": "គ្រឿងញៀន ហាមបញ្ចូល EM3527172 https://t.me/c/3675711084/9256/10774"},
        {"name": "W5710083", "note": "FAKE ហាមបញ្ចូល PATEL NIKUNJBHAI ARVINDBHAI https://t.me/c/3875174011/369"},
        {"name": "PATEL NIKUNJBHAI ARVINDBHAI", "note": "FAKE ហាមបញ្ចូល W5710083 https://t.me/c/3875174011/369"},
        {"name": "EF3280299", "note": "FAKE ហាមបញ្ចូល ZHANG ENBAO https://t.me/c/3875174011/369"},
        {"name": "ZHANG ENBAO", "note": "FAKE ហាមបញ្ចូល EF3280299 https://t.me/c/3875174011/369"},
        {"name": "EF6811755", "note": "FAKE ហាមបញ្ចូល YANG HONGMIN https://t.me/c/3875174011/337"},
        {"name": "YANG HONGMIN", "note": "FAKE ហាមបញ្ចូល EF6811755 https://t.me/c/3875174011/337"},
        {"name": "E3316182", "note": "FAKE ហាមបញ្ចូល AKBAR SATRIA PRADANA SARAGIH https://t.me/c/3875174011/334"},
        {"name": "AKBAR SATRIA PRADANA SARAGIH", "note": "FAKE ហាមបញ្ចូល E3316182 https://t.me/c/3875174011/334"},
        {"name": "EQ3823487", "note": "FAKE ហាមបញ្ចូល LI XING https://t.me/c/3875174011/332"},
        {"name": "LI XING", "note": "FAKE ហាមបញ្ចូល EQ3823487 https://t.me/c/3875174011/332"},
        {"name": "EP4478833", "note": "FAKE ហាមបញ្ចូល MA YUANBIN https://t.me/c/3875174011/320"},
        {"name": "MA YUANBIN", "note": "FAKE ហាមបញ្ចូល EP4478833 https://t.me/c/3875174011/330"},
        {"name": "ER6883244", "note": "FAKE VISA ហាមបញ្ចូល WANG QI https://t.me/c/3875174011/327"},
        {"name": "WANG QI", "note": "FAKE VISA ហាមបញ្ចូល ER6883244 https://t.me/c/3875174011/327"},
        {"name": "AD8835821", "note": "FAKE ហាមបញ្ចូល JASPER https://t.me/c/3875174011/317"},
        {"name": "JASPER", "note": "FAKE ហាមបញ្ចូល AD8835821 https://t.me/c/3875174011/317"},
        {"name": "E7467408", "note": "FAKE ហាមបញ្ចូល HENDRA https://t.me/c/3875174011/314"},
        {"name": "HENDRA", "note": "FAKE ហាមបញ្ចូល E7467408 https://t.me/c/3875174011/314"},
        {"name": "EN9748492", "note": "FAKE ហាមបញ្ចូល FANG HAIRONG https://t.me/c/3875174011/310"},
        {"name": "FANG HAIRONG", "note": "FAKE ហាមបញ្ចូល EN9748492 https://t.me/c/3875174011/310"},
        {"name": "P00409278", "note": "FAKE ហាមបញ្ចូល TRAN THI THUY TRANG https://t.me/c/3875174011/307"},
        {"name": "TRAN THI THUY TRANG", "note": "FAKE ហាមបញ្ចូល P00409278 https://t.me/c/3875174011/307"},
        {"name": "AR296151", "note": "FAKE ហាមបញ្ចូល PITCHAI PILLAI DHANASEKARAN https://t.me/c/3875174011/285"},
        {"name": "PITCHAI PILLAI DHANASEKARAN", "note": "FAKE ហាមបញ្ចូល AR296151 https://t.me/c/3875174011/285"},
        {"name": "EN0457371", "note": "FAKE ហាមបញ្ចូល SONG XIAOBING https://t.me/c/3875174011/277"},
        {"name": "SONG XIAOBING", "note": "FAKE ហាមបញ្ចូល EN0457371 https://t.me/c/3875174011/277"},
        {"name": "EK2379792", "note": "FAKE ហាមបញ្ចូល HUANG ZIHUA https://t.me/c/3875174011/276"},
        {"name": "HUANG ZIHUA", "note": "FAKE ហាមបញ្ចូល EK2379792 https://t.me/c/3875174011/276"},
        {"name": "X6163783", "note": "FAKE ហាមបញ្ចូល AGI RUSDIANSYAH https://t.me/c/3875174011/269"},
        {"name": "AGI RUSDIANSYAH", "note": "FAKE ហាមបញ្ចូល X6163783 https://t.me/c/3875174011/269"},
        {"name": "X6753210", "note": "FAKE ហាមបញ្ចូល ELVI FRANSISCA https://t.me/c/3875174011/265"},
        {"name": "ELVI FRANSISCA", "note": "FAKE ហាមបញ្ចូល X6753210 https://t.me/c/3875174011/265"},
        {"name": "E4731291", "note": "FAKE ហាមបញ្ចូល MHD HAJI SURYA https://t.me/c/3875174011/267"},
        {"name": "MHD HAJI SURYA", "note": "FAKE ហាមបញ្ចូល E4731291 https://t.me/c/3875174011/267"},
        {"name": "EP7891566", "note": "FAKE ហាមបញ្ចូល CHEN WEITING https://t.me/c/3875174011/247"},
        {"name": "CHEN WEITING", "note": "FAKE ហាមបញ្ចូល EP7891566 https://t.me/c/3875174011/247"},
        {"name": "PA0505553", "note": "FAKE ហាមបញ្ចូល THOUMMANEEVONG NABDAO https://t.me/c/3875174011/238"},
        {"name": "THOUMMANEEVONG NABDAO", "note": "FAKE ហាមបញ្ចូល PA0505553 https://t.me/c/3875174011/238"},
        {"name": "EE4244174", "note": "FAKE ហាមបញ្ចូល FENG YUPING https://t.me/c/3875174011/206"},
        {"name": "FENG YUPING", "note": "FAKE ហាមបញ្ចូល EE4244174 https://t.me/c/3875174011/206"},
        {"name": "EQ2350861", "note": "FAKE ហាមបញ្ចូល GUO CHUNLING https://t.me/c/3875174011/202"},
        {"name": "GUO CHUNLING", "note": "FAKE ហាមបញ្ចូល EQ2350861 https://t.me/c/3875174011/202"},
        {"name": "EM9424036", "note": "FAKE ហាមបញ្ចូល YING LINGMA https://t.me/c/3604999601/22"},
        {"name": "YING LINGMA", "note": "FAKE ហាមបញ្ចូល EM9424036 https://t.me/c/3604999601/22"},
        {"name": "ER3727125", "note": "FAKE ហាមបញ្ចូល LI PENGXIN https://t.me/c/3875174011/397"},
        {"name": "LI PENGXIN", "note": "FAKE ហាមបញ្ចូល ER3727125 https://t.me/c/3875174011/397"},
        {"name": "EL1119783", "note": "FAKE ហាមបញ្ចូល LIU ZHONGJI https://t.me/c/3875174011/199"},
        {"name": "LIU ZHONGJI", "note": "FAKE ហាមបញ្ចូល EL1119783 https://t.me/c/3875174011/199"},
        {"name": "EJ4531730", "note": "FAKE ហាមបញ្ចូល ZHAO FANGFANG https://t.me/c/3875174011/197"},
        {"name": "ZHAO FANGFANG", "note": "FAKE ហាមបញ្ចូល EJ4531730 https://t.me/c/3875174011/197"},
        {"name": "EJ6022002", "note": "FAKE ហាមបញ្ចូល YE RIXIN https://t.me/c/3875174011/195"},
        {"name": "YE RIXIN", "note": "FAKE ហាមបញ្ចូល EJ6022002 https://t.me/c/3875174011/195"},
        {"name": "EQ8403515", "note": "FAKE ហាមបញ្ចូល BI GUIHUA https://t.me/c/3875174011/193"},
        {"name": "BI GUIHUA", "note": "FAKE ហាមបញ្ចូល EQ8403515 https://t.me/c/3875174011/193"},
        {"name": "EK5441434", "note": "FAKE ហាមបញ្ចូល GAO LIUPING https://t.me/c/3875174011/191"},
        {"name": "GAO LIUPING", "note": "FAKE ហាមបញ្ចូល EK5441434 https://t.me/c/3875174011/191"},
        {"name": "E97824116", "note": "FAKE ហាមបញ្ចូល ZHANG YING https://t.me/c/3875174011/189"},
        {"name": "ZHANG YING", "note": "FAKE ហាមបញ្ចូល E97824116 https://t.me/c/3875174011/189"},
        {"name": "EP0233506", "note": "FAKE ហាមបញ្ចូល JIANG FENGHUAN https://t.me/c/3875174011/187"},
        {"name": "JIANG FENGHUAN", "note": "FAKE ហាមបញ្ចូល EP0233506 https://t.me/c/3875174011/187"},
        {"name": "EQ8409227", "note": "FAKE ហាមបញ្ចូល DU GENRONG https://t.me/c/3875174011/185"},
        {"name": "DU GENRONG", "note": "FAKE ហាមបញ្ចូល EQ8409227 https://t.me/c/3875174011/185"},
        {"name": "EL8734880", "note": "FAKE ហាមបញ្ចូល GONG ZHENJIANG https://t.me/c/3875174011/183"},
        {"name": "GONG ZHENJIANG", "note": "FAKE ហាមបញ្ចូល EL8734880 https://t.me/c/3875174011/183"},
        {"name": "EM8725555", "note": "FAKE ហាមបញ្ចូល YAO ZHANSHENG https://t.me/c/3875174011/173"},
        {"name": "YAO ZHANSHENG", "note": "FAKE ហាមបញ្ចូល EM8725555 https://t.me/c/3875174011/173"},
        {"name": "EN3732143", "note": "FAKE ហាមបញ្ចូល SONG XIAOLING https://t.me/c/3875174011/171"},
        {"name": "SONG XIAOLING", "note": "FAKE ហាមបញ្ចូល EN3732143 https://t.me/c/3875174011/171"},
        {"name": "EQ8401846", "note": "FAKE ហាមបញ្ចូល DING XUE https://t.me/c/3875174011/179"},
        {"name": "DING XUE", "note": "FAKE ហាមបញ្ចូល EQ8401846 https://t.me/c/3875174011/179"},
        {"name": "EQ8400856", "note": "FAKE ហាមបញ្ចូល GAO FENGYANG https://t.me/c/3875174011/175"},
        {"name": "GAO FENGYANG", "note": "FAKE ហាមបញ្ចូល EQ8400856 https://t.me/c/3875174011/175"},
        {"name": "EN3732142", "note": "FAKE ហាមបញ្ចូល YANG CHUNYI https://t.me/c/3875174011/181"},
        {"name": "YANG CHUNYI", "note": "FAKE ហាមបញ្ចូល EN3732142 https://t.me/c/3875174011/181"},
        {"name": "EP0291032", "note": "FAKE ហាមបញ្ចូល CHEN GUANG https://t.me/c/3875174011/177"},
        {"name": "CHEN GUANG", "note": "FAKE ហាមបញ្ចូល EP0291032 https://t.me/c/3875174011/177"},
        {"name": "EP4639488", "note": "FAKE ហាមបញ្ចូល LU SHANGJIN"},
        {"name": "LU SHANGJIN", "note": "FAKE ហាមបញ្ចូល EP4639488"},
        {"name": "EM3167265", "note": "FAKE VISA PENG HUI https://t.me/c/3875174011/346"},
        {"name": "PENG HUI", "note": "FAKE VISA EM3167265 https://t.me/c/3875174011/346"},
        {"name": "ER3760816", "note": "FAKE VISA ZOU HAIFEI https://t.me/c/3875174011/350"},
        {"name": "ZOU HAIFEI", "note": "FAKE VISA ER3760816 https://t.me/c/3875174011/350"},
        {"name": "RV0209348", "note": "FAKE VISA WANG YUCHEN https://t.me/c/3875174011/373"},
        {"name": "WANG YUCHEN", "note": "FAKE VISA RV0209348 https://t.me/c/3875174011/373"},
        {"name": "E77335219", "note": "FAKE VISA ZHANG YACHAO https://t.me/c/3875174011/380"},
        {"name": "ZHANG YACHAO", "note": "FAKE VISA E77335219 https://t.me/c/3875174011/380"},
        {"name": "ER4208386", "note": "FAKE VISA CHEN LIUBAO https://t.me/c/3854502836/586"},
        {"name": "CHEN LIUBAO", "note": "FAKE VISA ER4208386 https://t.me/c/3854502836/586"},
        {"name": "EP1745855", "note": "FAKE VISA ZHANG ZHENGLU https://t.me/c/3875174011/254"},
        {"name": "ZHANG ZHENGLU", "note": "FAKE VISA EP1745855 https://t.me/c/3875174011/254"},
        {"name": "A72229751", "note": "FAKE PASSPORT TEW CHOON WEI https://t.me/c/3675711084/5795/9999"},
        {"name": "TEW CHOON WEI", "note": "FAKE PASSPORT A72229751 https://t.me/c/3675711084/5795/9999"},
        {"name": "EQ9728501", "note": "FAKE PASSPORT MA BINJI https://t.me/c/3875174011/209"},
        {"name": "MA BINJI", "note": "FAKE PASSPORT EQ9728501 https://t.me/c/3875174011/209"},
        {"name": "ER1309824", "note": "FAKE PASSPORT WANG QIANG https://t.me/c/3875174011/235"},
        {"name": "WANG QIANG", "note": "FAKE PASSPORT ER1309824 https://t.me/c/3875174011/235"},
        {"name": "C9920463", "note": "FAKE VISA NURVERA KURNIAWAN https://t.me/c/3875174011/224"},
        {"name": "NURVERA KURNIAWAN", "note": "FAKE VISA C9920463 https://t.me/c/3875174011/224"},
        {"name": "X7920823", "note": "FAKE VISA FAHREZI SUWANDANA https://t.me/c/3875174011/211"},
        {"name": "FAHREZI SUWANDANA", "note": "FAKE VISA X7920823 https://t.me/c/3875174011/211"},
        {"name": "EQ8998866", "note": "FAKE PASSPORT CHEN XINGLIN https://t.me/c/3875174011/213"},
        {"name": "CHEN XINGLIN", "note": "FAKE PASSPORT EQ8998866 https://t.me/c/3875174011/213"},
        {"name": "ER5616662", "note": "បន្លំឯកសារវីសា ZHOU YUNHON https://t.me/c/3733767420/4818"},
        {"name": "ZHOU YUNHONG", "note": "បន្លំឯកសារវីសា ER5616662 https://t.me/c/3733767420/4818"},
        {"name": "551916339", "note": "ខូចត្រូវ​បាន​ផាក​ពិន័យ បន្ទាប់ពីបានបំផ្លាញអគារបេតិកភណ្ឌអូស្ត្រាលីនៅឆ្នាំ2020"},
        {"name": "GUERIN WADE WILIAM", "note": "ខូចត្រូវ​បាន​ផាក​ពិន័យ បន្ទាប់ពីបានបំផ្លាញអគារបេតិកភណ្ឌអូស្ត្រាលីនៅឆ្នាំ2020"},
        {"name": "EK9337841", "note": "CBM PEI XIAOLONG (FAKE VISA 25-JUNE-2025)"},
        {"name": "34500444", "note": "VPPT-E1083 (ជនជាតិ NORWAY ​ស្រដៀងគាត់ជាអ្នកបកប្រែ អ្នកនិពន្ធ)"},
        {"name": "677442959", "note": "SSR-619 (ជនជាតិ American អ្នកជំនាញបច្ចេកទេសវារីវប្បកម្មនៅCAST Cambodia)"},
        {"name": "YB5457292", "note": "VPPT-E1082 (ជនជាតិ Italian)"},
        {"name": "YB4386676", "note": "VPPT-E1082 (ជនជាតិ Italian Streetphotography)"},
        {"name": "642788769", "note": "JAN-02 (លេង game ធើ្វ Video នឹង មាន Tiktok)"},
        {"name": "A35029510", "note": "VPPT-E1068 (Project Managementនៅក្រុមហ៊ុនGoogle)"},
        {"name": "21CA13437", "note": "SHP-P6303 (នាយកប្រតិបត្តិនៅ GUIRAUD MOUSSE)"},
        {"name": "22AD02682", "note": "FRENCH"},
        {"name": "GA9335239", "note": "ជនជាតិ Belgian បងម្នាក់នេះគាត់អ្នកផ្សព្វផ្សាយពី ម្ហូប ប្រាសាទ"},
        {"name": "759328609", "note": "ជនជាតិ​ Russia"},
        {"name": "PA6674620", "note": "ជនជាតិ​ Australian NEWS"},
        {"name": "551538429", "note": "youtube"},
        {"name": "N112698", "note": "ទំនាក់ទំនងព័ត៌មាន LIU-H2666"},
        {"name": "664178369", "note": "(​VPPT-E1009 គាត់ធ្លាប់ធ្វើខាងព័ត៌មាន​ និង បកប្រែអត្ថបទ)"},
        {"name": "TAN CHE HONG", "note": "ហាមបញ្ចូល"},
        {"name": "CHEONG TWON FONG", "note": "ហាមបញ្ចូល"},
        {"name": "TAN HONG LEONG", "note": "ហាមបញ្ចូល"},
        {"name": "ZHENG HAO WONG", "note": "ហាមបញ្ចូល"},
        {"name": "TANJA CARMEN FRIEDEL PRINZ", "note": "ហាមបញ្ចូល"},
        {"name": "C36K3HV4J", "note": "ហាមបញ្ចូល"},
        {"name": "GERRIT PRINZ", "note": "ហាមបញ្ចូល"},
        {"name": "C36KG733Z", "note": "ហាមបញ្ចូល"},
        {"name": "MASIMO CHRISTIAN KAPPES WEIB", "note": "ហាមបញ្ចូល"},
        {"name": "CAO DAC THUC", "note": "ហាមបញ្ចូល"},
        {"name": "MAI VAN PHONG", "note": "ហាមបញ្ចូល"},
        {"name": "VU XUAN TUNG", "note": "ហាមបញ្ចូល"},
        {"name": "C8WZKLVW4", "note": "ហាមបញ្ចូល"},
        {"name": "NAJDUCH GWENAELLE", "note": "ហាមបញ្ចូល"},
        {"name": "LAO LENGBOU", "note": "ហាមបញ្ចូល"},
        {"name": "PURICELLI FRANCESCA", "note": "SSR"},
        {"name": "YB7603751", "note": "B-LONG-2161 អង្គការ"},
        {"name": "642962617", "note": "VPPT-E910 Producer en Eden Cafe"},
        {"name": "AA3467836", "note": "B-LONG-2182"},
        {"name": "A10716782", "note": "B-LONG-2182 English Teacher"},
        {"name": "21FV01774", "note": "VPPT-E922 C-Level Sales & Management Expert"},
        {"name": "566435361", "note": "LVK-158 ម្នាក់នេះដូចខាងអង្កការបង"},
        {"name": "20FV05699", "note": "LVK-155 Medical Student"},
        {"name": "517232103", "note": "SSR-614 Search in google : Guide"},
        {"name": "553745721", "note": "SSR-614 Search in google : Lawyer"},
        {"name": "AN447178", "note": "TAG-SO2428 Position:Communications consultant"},
        {"name": "683259703", "note": "TAG-SO2442 youtuber"},
        {"name": "AR409862", "note": "TAG-SO2443"},
        {"name": "642936802", "note": "SSR-613"},
        {"name": "N14758506", "note": "TAG-SO2452"},
        {"name": "A06551235", "note": "TAG-SO2451 ម្នាក់នេះដូចខាងអង្កការបង"},
        {"name": "566773531", "note": "TAG-SO2449 Check ឃើញបង មាន tiktok មាន ig"},
        {"name": "BDHRLH9K5", "note": "R&D Manager/Company: OYIKA CO LTD"},
        {"name": "C5MP5GWJ2", "note": "Country Manager/Company: OYIKA CO LTD"},
        {"name": "FG194539", "note": "Search in google :Senior Chinese-English Translator"},
        {"name": "16CH82811", "note": "ASEAN Development Advisor"},
        {"name": "A27400161", "note": "Can't Submit"},
        {"name": "CRUZ MORALES NICOLE", "note": "(ម្នាក់នេះអ្នកយកព័ត៍មាន)"},
        {"name": "XE82045", "note": "(ម្នាក់នេះអ្នកយកព័ត៍មាន)"},
        {"name": "FD7405215", "note": "(​ អ្នកសារព័ត៌មាន )"},
        {"name": "ET7041524", "note": "(​ អ្នកសារព័ត៌មាន )"},
        {"name": "127821629", "note": "(​ ដូចអង្ករការ )"},
        {"name": "21CH83756", "note": "(​ YOUTUBER )"},
        {"name": "GK614935", "note": "(​ YOUTUBER )"},
        {"name": "FA7995577", "note": "(​ អ្នកប្រដាល )"},
        {"name": "765304661", "note": "(​ MISSION PERSON )"},
        {"name": "VE55656", "note": "(​ ម្នាក់នេះខាងអង្កការបង ព្រោះថតជាមួយក្មេងៗ និងមនុស្សចាស់ )"},
        {"name": "MICHAEL HAO NHEN TU", "note": "(​ ហាមបញ្ចូល )"},
        {"name": "HAO NHEN TU", "note": "(​ ហាមបញ្ចូល )"},
        {"name": "ALIAS VAN LUONG TU", "note": "(​ ហាមបញ្ចូល )"},
        {"name": "RA4718801", "note": "(​ ហាមបញ្ចូល )"}
    ],
    "greenWords": [
        "`2025",
        "`2026",
        "K-2025"
    ],
    "blockedDates": [
        "01/01/1990",
        "10/10/1990",
        "05/09/1968",
        "06/10/1994",
        "12/10/1998",
        "01011990"
    ]
}























